[
  {
    "id": 8235,
    "storedMatchingId": 0,
    "searchingFor": 0,
    "suburbId": 1929,
    "suburbName": "Handskeryd",
    "cityId": 184,
    "cityName": "Nässjö",
    "address": "Handskerydsvägen 31",
    "addressCity": "Nässjö",
    "contractType": 0,
    "contractLength": 3,
    "otherLength": "0",
    "area": 74,
    "rooms": 2,
    "rent": 5950,
    "warm": 2,
    "elevator": false,
    "balcony": true,
    "floor1Sub": false,
    "floor1Ground": false,
    "floor1Stairs": false,
    "attic": true,
    "duplex": false,
    "furnished": false,
    "entryDate": "2021-09-01",
    "floor": 3,
    "reference": "",
    "postalCode": "57140",
    "otherInfo": "Stor och ljus vindsvåning med balkong, kvällssol och fin utsikt över Handskerydssjön.\n\nLägenheten har bra förvaringsmöjligheter. \n\nHelkaklat badrum och kök med diskmaskin.\n\nParkeringsplats ingår.\n\nTvättstuga med tvättmaskin, torktumlare och torkrum.\n\nFörrådsutrymme även i källaren.\n\nMöjlighet finns för att hyra garage.",
    "adText": "Lägenhet om 2rok i Nässjö, Handskeryd. Stor och ljus vindsvåning med balkong, kvällssol och fin utsikt över Handskerydssjön. Lägenheten har bra förvaringsmöjligheter. Helkaklat badrum och kök med diskmaskin. Parkeringsplats ingår. Tvättstuga med tvättmaskin, torktumlare och torkrum. Förrådsutrymme även i källaren. Möjlighet finns för att hyra garage. @bostadsregistret #bostadsregistret ",
    "statusText": "Published",
    "statusCode": 1,
    "hidden": false,
    "comments": "",
    "mayManageApplicants": false,
    "registerIdSelectedByLandlord": 0,
    "rented": 0,
    "cancelled": 0,
    "copyright": "Copyright Bostadsregistret AB",
    "timeWhenLandlordMaySeeApplicants": 1623448800
  },
  {
    "id": 8231,
    "storedMatchingId": 0,
    "searchingFor": 0,
    "suburbId": 4,
    "suburbName": "Bankeryd",
    "cityId": 9,
    "cityName": "Jönköping",
    "address": "Ågatan 10",
    "addressCity": "Bankeryd",
    "contractType": 0,
    "contractLength": 3,
    "otherLength": "0",
    "area": 70,
    "rooms": 2,
    "rent": 7200,
    "warm": 2,
    "elevator": false,
    "balcony": false,
    "floor1Sub": false,
    "floor1Ground": false,
    "floor1Stairs": false,
    "attic": false,
    "duplex": false,
    "furnished": false,
    "entryDate": "2021-08-01",
    "floor": 2,
    "reference": "",
    "postalCode": "56433",
    "otherInfo": "",
    "adText": "Lägenhet om 2rok i Jönköping, Bankeryd. @bostadsregistret #bostadsregistret ",
    "statusText": "Published",
    "statusCode": 1,
    "hidden": false,
    "comments": "",
    "mayManageApplicants": false,
    "registerIdSelectedByLandlord": 0,
    "rented": 0,
    "cancelled": 0,
    "copyright": "Copyright Bostadsregistret AB",
    "timeWhenLandlordMaySeeApplicants": 1623276000
  },
  {
    "id": 8227,
    "storedMatchingId": 0,
    "searchingFor": 0,
    "suburbId": 1681,
    "suburbName": "Centralt",
    "cityId": 184,
    "cityName": "Nässjö",
    "address": "Fridhemsgatan 4 ",
    "addressCity": "Nässjö ",
    "contractType": 0,
    "contractLength": 3,
    "otherLength": "0",
    "area": 88,
    "rooms": 3,
    "rent": 7898,
    "warm": 2,
    "elevator": false,
    "balcony": true,
    "floor1Sub": false,
    "floor1Ground": false,
    "floor1Stairs": false,
    "attic": false,
    "duplex": false,
    "furnished": false,
    "entryDate": "2021-09-01",
    "floor": 1,
    "reference": "Från tidigare hyresvärd ",
    "postalCode": "57136",
    "otherInfo": "Tillgång till trädgård. Finns garage att hyra intill huset ",
    "adText": "Lägenhet om 3rok i Centrala Nässjö. Finns garage att hyra intill huset. Stor balkong på 12 Kvadratmeter med trappa till trärgåd. Inga betalningsanmärkning är uppskattat @bostadsregistret #bostadsregistret",
    "statusText": "Published",
    "statusCode": 1,
    "hidden": false,
    "comments": "",
    "mayManageApplicants": true,
    "registerIdSelectedByLandlord": 0,
    "rented": 0,
    "cancelled": 0,
    "copyright": "Copyright Bostadsregistret AB",
    "timeWhenLandlordMaySeeApplicants": 1622757600
  },
  {
    "id": 8226,
    "storedMatchingId": 0,
    "searchingFor": 0,
    "suburbId": 1681,
    "suburbName": "Centralt",
    "cityId": 184,
    "cityName": "Nässjö",
    "address": "Gustavsbergsgatan 9 ",
    "addressCity": "Nässjö",
    "contractType": 0,
    "contractLength": 3,
    "otherLength": "0",
    "area": 82,
    "rooms": 3,
    "rent": 6337,
    "warm": 2,
    "elevator": false,
    "balcony": false,
    "floor1Sub": false,
    "floor1Ground": false,
    "floor1Stairs": false,
    "attic": false,
    "duplex": false,
    "furnished": false,
    "entryDate": "2021-10-01",
    "floor": 2,
    "reference": "",
    "postalCode": "57133",
    "otherInfo": "Tvätt och torktumlare i lägenheten\nDiskmaskin\n\nLägenheten finns tillgänglig tidigare om intresse finns ",
    "adText": "Lägenhet om 3rok i Centrala Nässjö. Tvätt och torktumlare i lägenheten. Diskmaskin. Lägenheten finns tillgänglig tidigare om intresse finns. För fler interiörbilder och exteriörbild tryck på fler bilder. @bostadsregistret #bostadsregistret ",
    "statusText": "Published",
    "statusCode": 1,
    "hidden": false,
    "comments": "",
    "mayManageApplicants": true,
    "registerIdSelectedByLandlord": 0,
    "rented": 0,
    "cancelled": 0,
    "copyright": "Copyright Bostadsregistret AB",
    "timeWhenLandlordMaySeeApplicants": 1623103200
  },
  {
    "id": 8224,
    "storedMatchingId": 0,
    "searchingFor": 0,
    "suburbId": 1681,
    "suburbName": "Centralt",
    "cityId": 184,
    "cityName": "Nässjö",
    "address": "Kolonigatan 1",
    "addressCity": "Nässjö ",
    "contractType": 0,
    "contractLength": 3,
    "otherLength": "0",
    "area": 95,
    "rooms": 3,
    "rent": 7130,
    "warm": 2,
    "elevator": false,
    "balcony": true,
    "floor1Sub": false,
    "floor1Ground": false,
    "floor1Stairs": false,
    "attic": false,
    "duplex": false,
    "furnished": false,
    "entryDate": "2021-09-01",
    "floor": 3,
    "reference": "",
    "postalCode": "57132",
    "otherInfo": "Stor ljus 3a som i golvyta är ca 105 kvm, men 95 kvm då snedtak förekommer. Badrum renoverades 2018, tvättmaskin finns. Köket har varmluftsugn och diskmaskin. Stor balkong som är ca 18 kvm, elektrisk markis över 5 meter av balkongen.\nTidigare tillträde till 1/7 är möjlig, alt enligt ök, tillträde tidigare än 1/9 kommer att prioriteras. ",
    "adText": "Lägenhet om 3rok i Centrala Nässjö. Stor ljus 3a som i golvyta är ca 105 kvm, men 95 kvm då snedtak förekommer. Badrum renoverades 2018, tvättmaskin finns. Köket har varmluftsugn och diskmaskin. Stor balkong som är ca 18 kvm, elektrisk markis över 5 meter av balkongen. Tidigare tillträde till 1/7 är möjlig, alt enligt ök, tillträde tidigare än 1/9 kommer att prioriteras. Tryck på fler bilder för fler interiörbilder samt bild från balkongen. @bostadsregistret #bostadsregistret ",
    "statusText": "Published",
    "statusCode": 1,
    "hidden": false,
    "comments": "",
    "mayManageApplicants": true,
    "registerIdSelectedByLandlord": 0,
    "rented": 0,
    "cancelled": 0,
    "copyright": "Copyright Bostadsregistret AB",
    "timeWhenLandlordMaySeeApplicants": 1623103200
  },
  {
    "id": 8225,
    "storedMatchingId": 0,
    "searchingFor": 0,
    "suburbId": 1929,
    "suburbName": "Handskeryd",
    "cityId": 184,
    "cityName": "Nässjö",
    "address": "Queckfeldtsgatan 54",
    "addressCity": "NÄSSJÖ",
    "contractType": 0,
    "contractLength": 3,
    "otherLength": "0",
    "area": 64,
    "rooms": 2,
    "rent": 6300,
    "warm": 2,
    "elevator": false,
    "balcony": false,
    "floor1Sub": false,
    "floor1Ground": false,
    "floor1Stairs": false,
    "attic": false,
    "duplex": false,
    "furnished": false,
    "entryDate": "2021-09-01",
    "floor": 2,
    "reference": "",
    "postalCode": "57140",
    "otherInfo": "En fräsch lägenhet till uthyrning i Nässjö med inglasad balkong \n\nLägenheten är en 2:a med 64 kvm2  bestående av en rymlig inglasad balkongen, sovrum med klädkammare och vardagsrum, fullutrustad kök, fräscht badrum med duschkabin. Stor och välkomnade hall med goda förvaringsutrymmen.  \n\nLägenheten och fastigheten har solläge tillhörande en charmig trädgård som ger en villa känsla.\n\nLägenheten befinner sig i Handskeryd i en lungt och fint område, tvärsemot pizzeria Viktoria med gångavstånd mot ICA och Nässjö stad.\n\nHyresgäster som söks ska vara skötsamma med en stabil inkomst\n\nVarmhyra inkl. parkering-plats\n\nLedig från 1:a September  \n",
    "adText": "Lägenhet om 2rok i Nässjö, Handskeryd. En fräsch lägenhet till uthyrning i Nässjö med inglasad balkong Lägenheten är en 2:a med 64 kvm2 bestående av en rymlig inglasad balkongen, sovrum med klädkammare och vardagsrum, fullutrustad kök, fräscht badrum med duschkabin. Stor och välkomnade hall med goda förvaringsutrymmen. Lägenheten och fastigheten har solläge tillhörande en charmig trädgård. Lägenheten befinner sig i Handskeryd i en lungt och fint område, tvärsemot pizzeria Viktoria, på en bussgata med gångavstånd mot ICA och Nässjö stad. Hyresgäster önskas vara skötsamma med en stabil inkomst Ledig från 1:a September. @bostadsregistret #bostadsregistret ",
    "statusText": "Published",
    "statusCode": 1,
    "hidden": false,
    "comments": "",
    "mayManageApplicants": true,
    "registerIdSelectedByLandlord": 0,
    "rented": 0,
    "cancelled": 0,
    "copyright": "Copyright Bostadsregistret AB",
    "timeWhenLandlordMaySeeApplicants": 1623103200
  },
  {
    "id": 8219,
    "storedMatchingId": 0,
    "searchingFor": 0,
    "suburbId": 1927,
    "suburbName": "Åker",
    "cityId": 184,
    "cityName": "Nässjö",
    "address": "Bäckgatan 24",
    "addressCity": "Nässjö",
    "contractType": 0,
    "contractLength": 3,
    "otherLength": "0",
    "area": 100,
    "rooms": 4,
    "rent": 8268,
    "warm": 2,
    "elevator": false,
    "balcony": true,
    "floor1Sub": false,
    "floor1Ground": false,
    "floor1Stairs": false,
    "attic": false,
    "duplex": false,
    "furnished": false,
    "entryDate": "2021-09-01",
    "floor": 1,
    "reference": "",
    "postalCode": "57141",
    "otherInfo": "Fräsch lägenhet\nFinns garage att hyra i fastigheten.",
    "adText": "Lägenhet om 4rok i Nässjö, Åker. Balkong. Fräsch lägenhet. Garage finns att hyra i fastigheten. @bostadsregistret #bostadsregistret ",
    "statusText": "Published",
    "statusCode": 1,
    "hidden": false,
    "comments": "",
    "mayManageApplicants": true,
    "registerIdSelectedByLandlord": 0,
    "rented": 0,
    "cancelled": 0,
    "copyright": "Copyright Bostadsregistret AB",
    "timeWhenLandlordMaySeeApplicants": 1623016800
  },
  {
    "id": 8218,
    "storedMatchingId": 0,
    "searchingFor": 0,
    "suburbId": 1927,
    "suburbName": "Åker",
    "cityId": 184,
    "cityName": "Nässjö",
    "address": "Stolmakaregatan 21",
    "addressCity": "Nässjö",
    "contractType": 0,
    "contractLength": 3,
    "otherLength": "0",
    "area": 90,
    "rooms": 3,
    "rent": 7429,
    "warm": 2,
    "elevator": false,
    "balcony": true,
    "floor1Sub": false,
    "floor1Ground": false,
    "floor1Stairs": false,
    "attic": false,
    "duplex": false,
    "furnished": false,
    "entryDate": "2021-09-01",
    "floor": 2,
    "reference": "",
    "postalCode": "57141",
    "otherInfo": "Finns garage att hyra i Bäckgatan 24",
    "adText": "Lägenhet om 3rok i Nässjö, Åker. Balkong. Garage finns att hyra i Bäckgatan 24. @bostadsregistret #bostadsregistret ",
    "statusText": "Published",
    "statusCode": 1,
    "hidden": false,
    "comments": "",
    "mayManageApplicants": true,
    "registerIdSelectedByLandlord": 0,
    "rented": 0,
    "cancelled": 0,
    "copyright": "Copyright Bostadsregistret AB",
    "timeWhenLandlordMaySeeApplicants": 1623016800
  },
  {
    "id": 8217,
    "storedMatchingId": 0,
    "searchingFor": 0,
    "suburbId": 1939,
    "suburbName": "Malmbäck",
    "cityId": 184,
    "cityName": "Nässjö",
    "address": "Fabriksgatan 3",
    "addressCity": "Malmbäck",
    "contractType": 0,
    "contractLength": 3,
    "otherLength": "0",
    "area": 74,
    "rooms": 3,
    "rent": 5738,
    "warm": 2,
    "elevator": false,
    "balcony": true,
    "floor1Sub": false,
    "floor1Ground": false,
    "floor1Stairs": false,
    "attic": false,
    "duplex": false,
    "furnished": false,
    "entryDate": "2021-09-01",
    "floor": 2,
    "reference": "",
    "postalCode": "57168",
    "otherInfo": "Ledig from 1Sep. Gemensam tvättstuga I källaren. Fiber finns.",
    "adText": "Lägenhet om 3rok i Malmbäck, Nässjö kommun. Balkong. Ledig from 1Sep. Gemensam tvättstuga I källaren. Fiber finns. @bostadsregistret #bostadsregistret ",
    "statusText": "Published",
    "statusCode": 1,
    "hidden": false,
    "comments": "",
    "mayManageApplicants": true,
    "registerIdSelectedByLandlord": 0,
    "rented": 0,
    "cancelled": 0,
    "copyright": "Copyright Bostadsregistret AB",
    "timeWhenLandlordMaySeeApplicants": 1623016800
  },
  {
    "id": 8215,
    "storedMatchingId": 0,
    "searchingFor": 0,
    "suburbId": 1681,
    "suburbName": "Centralt",
    "cityId": 184,
    "cityName": "Nässjö",
    "address": "Kyrkogatan 3 B",
    "addressCity": "NÄSSJÖ",
    "contractType": 0,
    "contractLength": 3,
    "otherLength": "0",
    "area": 119,
    "rooms": 5,
    "rent": 9670,
    "warm": 2,
    "elevator": false,
    "balcony": true,
    "floor1Sub": false,
    "floor1Ground": false,
    "floor1Stairs": false,
    "attic": false,
    "duplex": true,
    "furnished": false,
    "entryDate": "2021-09-01",
    "floor": 2,
    "reference": "",
    "postalCode": "57132",
    "otherInfo": "",
    "adText": "Lägenhet om 5rok i Centrala Nässjö. Balkong. @bostadsregistret #bostadsregistret ",
    "statusText": "Published",
    "statusCode": 1,
    "hidden": false,
    "comments": "",
    "mayManageApplicants": true,
    "registerIdSelectedByLandlord": 0,
    "rented": 0,
    "cancelled": 0,
    "copyright": "Copyright Bostadsregistret AB",
    "timeWhenLandlordMaySeeApplicants": 1622930400
  },
  {
    "id": 8214,
    "storedMatchingId": 0,
    "searchingFor": 0,
    "suburbId": 1681,
    "suburbName": "Centralt",
    "cityId": 184,
    "cityName": "Nässjö",
    "address": "Rådhusgatan 54 C",
    "addressCity": "NÄSSJÖ",
    "contractType": 0,
    "contractLength": 3,
    "otherLength": "0",
    "area": 78,
    "rooms": 3,
    "rent": 6922,
    "warm": 2,
    "elevator": false,
    "balcony": true,
    "floor1Sub": false,
    "floor1Ground": false,
    "floor1Stairs": false,
    "attic": false,
    "duplex": false,
    "furnished": false,
    "entryDate": "2021-07-01",
    "floor": 3,
    "reference": "",
    "postalCode": "57132",
    "otherInfo": "2 st balkonger",
    "adText": "Lägenhet om 3rok i Centrala Nässjö. 2 Balkonger. @bostadsregistret #bostadsregistret ",
    "statusText": "Published",
    "statusCode": 1,
    "hidden": false,
    "comments": "",
    "mayManageApplicants": true,
    "registerIdSelectedByLandlord": 0,
    "rented": 0,
    "cancelled": 0,
    "copyright": "Copyright Bostadsregistret AB",
    "timeWhenLandlordMaySeeApplicants": 1622930400
  },
  {
    "id": 8213,
    "storedMatchingId": 0,
    "searchingFor": 0,
    "suburbId": 1681,
    "suburbName": "Centralt",
    "cityId": 184,
    "cityName": "Nässjö",
    "address": "Rådhusgatan 54 B",
    "addressCity": "NÄSSJÖ",
    "contractType": 0,
    "contractLength": 3,
    "otherLength": "0",
    "area": 96,
    "rooms": 3,
    "rent": 8196,
    "warm": 2,
    "elevator": true,
    "balcony": false,
    "floor1Sub": false,
    "floor1Ground": true,
    "floor1Stairs": false,
    "attic": false,
    "duplex": false,
    "furnished": false,
    "entryDate": "2021-08-01",
    "floor": 1,
    "reference": "",
    "postalCode": "57132",
    "otherInfo": "P-plats ingår",
    "adText": "Lägenhet om 3rok i Centrala Nässjö. Hiss. P-plats ingår. @bostadsregistret #bostadsregistret ",
    "statusText": "Published",
    "statusCode": 1,
    "hidden": false,
    "comments": "",
    "mayManageApplicants": true,
    "registerIdSelectedByLandlord": 0,
    "rented": 0,
    "cancelled": 0,
    "copyright": "Copyright Bostadsregistret AB",
    "timeWhenLandlordMaySeeApplicants": 1622930400
  },
  {
    "id": 8212,
    "storedMatchingId": 0,
    "searchingFor": 0,
    "suburbId": 3,
    "suburbName": "Huskvarna",
    "cityId": 9,
    "cityName": "Jönköping",
    "address": "Vattenfallsvägen 8",
    "addressCity": "Huskvarna ",
    "contractType": 0,
    "contractLength": 3,
    "otherLength": "0",
    "area": 86,
    "rooms": 3,
    "rent": 7645,
    "warm": 2,
    "elevator": false,
    "balcony": true,
    "floor1Sub": false,
    "floor1Ground": false,
    "floor1Stairs": true,
    "attic": false,
    "duplex": false,
    "furnished": false,
    "entryDate": "2021-09-01",
    "floor": 1,
    "reference": "",
    "postalCode": "56139",
    "otherInfo": "Parkering. Balkong. Diskmaskin ",
    "adText": "Lägenhet om 3rok  i Huskvarna, Jönköping. Balkong. Parkering. Diskmaskin. @bostadsregistret #bostadsregistret ",
    "statusText": "Published",
    "statusCode": 1,
    "hidden": false,
    "comments": "",
    "mayManageApplicants": true,
    "registerIdSelectedByLandlord": 0,
    "rented": 0,
    "cancelled": 0,
    "copyright": "Copyright Bostadsregistret AB",
    "timeWhenLandlordMaySeeApplicants": 1622930400
  },
  {
    "id": 8211,
    "storedMatchingId": 0,
    "searchingFor": 0,
    "suburbId": 1924,
    "suburbName": "Centrum",
    "cityId": 184,
    "cityName": "Nässjö",
    "address": "Köpmansgatan 4",
    "addressCity": "Nässjö",
    "contractType": 0,
    "contractLength": 3,
    "otherLength": "0",
    "area": 135,
    "rooms": 5,
    "rent": 9974,
    "warm": 2,
    "elevator": false,
    "balcony": true,
    "floor1Sub": false,
    "floor1Ground": false,
    "floor1Stairs": false,
    "attic": false,
    "duplex": false,
    "furnished": false,
    "entryDate": "2021-09-01",
    "floor": 2,
    "reference": "",
    "postalCode": "57132",
    "otherInfo": "Diskmaskin \n\nMöjlighet att flytta in tidigare finns",
    "adText": "Lägenhet om 5rok i Nässjö Centrum. Balkong. Diskmaskin. Stor lägenhet om i Nässjö Centrum. Nära till det mesta. Bör ses. Möjlighet till tidigare tillträde. @bostadsregistret #bostadsregistret ",
    "statusText": "Published",
    "statusCode": 1,
    "hidden": false,
    "comments": "",
    "mayManageApplicants": true,
    "registerIdSelectedByLandlord": 0,
    "rented": 0,
    "cancelled": 0,
    "copyright": "Copyright Bostadsregistret AB",
    "timeWhenLandlordMaySeeApplicants": 1622930400
  },
  {
    "id": 8210,
    "storedMatchingId": 0,
    "searchingFor": 0,
    "suburbId": 1924,
    "suburbName": "Centrum",
    "cityId": 184,
    "cityName": "Nässjö",
    "address": "Köpmansgatan 4",
    "addressCity": "Nässjö",
    "contractType": 0,
    "contractLength": 3,
    "otherLength": "0",
    "area": 100,
    "rooms": 2,
    "rent": 6800,
    "warm": 2,
    "elevator": false,
    "balcony": true,
    "floor1Sub": false,
    "floor1Ground": false,
    "floor1Stairs": false,
    "attic": false,
    "duplex": false,
    "furnished": false,
    "entryDate": "2021-09-01",
    "floor": 2,
    "reference": "",
    "postalCode": "57132",
    "otherInfo": "tvättmaskin ",
    "adText": "Lägenhet om 2rok i Nässjö Centrum. Balkong. Tvättmaskin. Stor lägenhet om 2rok i Nässjö Centrum. Nära till det mesta. Bör ses. @bostadsregistret #bostadsregistret ",
    "statusText": "Published",
    "statusCode": 1,
    "hidden": false,
    "comments": "",
    "mayManageApplicants": true,
    "registerIdSelectedByLandlord": 0,
    "rented": 0,
    "cancelled": 0,
    "copyright": "Copyright Bostadsregistret AB",
    "timeWhenLandlordMaySeeApplicants": 1622930400
  },
  {
    "id": 8209,
    "storedMatchingId": 0,
    "searchingFor": 0,
    "suburbId": 2240,
    "suburbName": "Skillingaryd",
    "cityId": 253,
    "cityName": "Vaggeryd",
    "address": "Läkaregatan 3",
    "addressCity": "Skillingaryd",
    "contractType": 0,
    "contractLength": 3,
    "otherLength": "0",
    "area": 52,
    "rooms": 2,
    "rent": 6716,
    "warm": 1,
    "elevator": true,
    "balcony": false,
    "floor1Sub": false,
    "floor1Ground": false,
    "floor1Stairs": false,
    "attic": false,
    "duplex": false,
    "furnished": false,
    "entryDate": "2021-09-01",
    "floor": 1,
    "reference": "A-1102",
    "postalCode": "56831",
    "otherInfo": "",
    "adText": "Lägenhet om 2rok i Skillingaryd, Vaggeryds kommun. Fint och nytt. Pendlingsavstånd till Jönköping, Vaggeryd, Värnamo och Sävsjö. @bostadsregistret #bostadsregistret ",
    "statusText": "Published",
    "statusCode": 1,
    "hidden": false,
    "comments": "",
    "mayManageApplicants": true,
    "registerIdSelectedByLandlord": 0,
    "rented": 0,
    "cancelled": 0,
    "copyright": "Copyright Bostadsregistret AB",
    "timeWhenLandlordMaySeeApplicants": 1622930400
  },
  {
    "id": 8207,
    "storedMatchingId": 0,
    "searchingFor": 0,
    "suburbId": 2240,
    "suburbName": "Skillingaryd",
    "cityId": 253,
    "cityName": "Vaggeryd",
    "address": "Läkaregatan 3",
    "addressCity": "Skillingaryd",
    "contractType": 0,
    "contractLength": 3,
    "otherLength": "0",
    "area": 35,
    "rooms": 1,
    "rent": 5115,
    "warm": 1,
    "elevator": false,
    "balcony": false,
    "floor1Sub": false,
    "floor1Ground": false,
    "floor1Stairs": false,
    "attic": false,
    "duplex": false,
    "furnished": false,
    "entryDate": "2021-06-01",
    "floor": 2,
    "reference": "B-1103",
    "postalCode": "56831",
    "otherInfo": "",
    "adText": "Lägenhet om 1rok i Skillingaryd, Vaggeryds kommun. Ny fin bostad. Pendlingsavstånd till Vaggeryd, Jönköping och Värnamo. @bostadsregistret #bostadsregistret ",
    "statusText": "Published",
    "statusCode": 1,
    "hidden": false,
    "comments": "",
    "mayManageApplicants": true,
    "registerIdSelectedByLandlord": 0,
    "rented": 0,
    "cancelled": 0,
    "copyright": "Copyright Bostadsregistret AB",
    "timeWhenLandlordMaySeeApplicants": 1622844000
  },
  {
    "id": 8202,
    "storedMatchingId": 0,
    "searchingFor": 0,
    "suburbId": 2478,
    "suburbName": "Bymarken",
    "cityId": 9,
    "cityName": "Jönköping",
    "address": "Björnebergsvägen 18 c",
    "addressCity": "Jönköping ",
    "contractType": 0,
    "contractLength": 2,
    "otherLength": "0",
    "area": 99,
    "rooms": 4,
    "rent": 12000,
    "warm": 2,
    "elevator": false,
    "balcony": false,
    "floor1Sub": false,
    "floor1Ground": false,
    "floor1Stairs": false,
    "attic": false,
    "duplex": false,
    "furnished": false,
    "entryDate": "2021-07-01",
    "floor": 2,
    "reference": "",
    "postalCode": "55312",
    "otherInfo": "",
    "adText": "Lägenhet om 4rok i Jönköping, Bymarken. @bostadsregistret #bostadsregistret ",
    "statusText": "Published",
    "statusCode": 1,
    "hidden": false,
    "comments": "",
    "mayManageApplicants": true,
    "registerIdSelectedByLandlord": 0,
    "rented": 0,
    "cancelled": 0,
    "copyright": "Copyright Bostadsregistret AB",
    "timeWhenLandlordMaySeeApplicants": 1622584800
  },
  {
    "id": 8199,
    "storedMatchingId": 0,
    "searchingFor": 0,
    "suburbId": 3,
    "suburbName": "Huskvarna",
    "cityId": 9,
    "cityName": "Jönköping",
    "address": "Mästaregatan 1C",
    "addressCity": "Huskvarna ",
    "contractType": 0,
    "contractLength": 3,
    "otherLength": "0",
    "area": 76,
    "rooms": 3,
    "rent": 7025,
    "warm": 2,
    "elevator": false,
    "balcony": true,
    "floor1Sub": false,
    "floor1Ground": false,
    "floor1Stairs": false,
    "attic": false,
    "duplex": false,
    "furnished": false,
    "entryDate": "2021-09-01",
    "floor": 2,
    "reference": "",
    "postalCode": "56131",
    "otherInfo": "Balkong. Kabel-tv ",
    "adText": "Lägenhet om 3rok i Huskvarna Centrum, Jönköping. Balkong. Kabel-tv. @bostadsregistret #bostadsregistret ",
    "statusText": "Published",
    "statusCode": 1,
    "hidden": false,
    "comments": "",
    "mayManageApplicants": true,
    "registerIdSelectedByLandlord": 0,
    "rented": 0,
    "cancelled": 0,
    "copyright": "Copyright Bostadsregistret AB",
    "timeWhenLandlordMaySeeApplicants": 1622498400
  },
  {
    "id": 8195,
    "storedMatchingId": 0,
    "searchingFor": 0,
    "suburbId": 2210,
    "suburbName": "Centrum",
    "cityId": 9,
    "cityName": "Jönköping",
    "address": "Östra Storgatan 14",
    "addressCity": "Jönköping",
    "contractType": 0,
    "contractLength": 3,
    "otherLength": "0",
    "area": 104,
    "rooms": 3,
    "rent": 13853,
    "warm": 2,
    "elevator": false,
    "balcony": true,
    "floor1Sub": false,
    "floor1Ground": false,
    "floor1Stairs": false,
    "attic": false,
    "duplex": false,
    "furnished": false,
    "entryDate": "2021-07-01",
    "floor": 3,
    "reference": "",
    "postalCode": "55321",
    "otherInfo": "Mycket fräsch lägenhet, totalrenoverad 2018. Egen tvm och tt.",
    "adText": "Lägenhet om 3rok i Jönköping Centrum. Balkong. Mitt i stan hittar ni denna stora 3:a med närhet till det mesta. @bostadsregistret #bostadsregistret ",
    "statusText": "Published",
    "statusCode": 1,
    "hidden": false,
    "comments": "",
    "mayManageApplicants": true,
    "registerIdSelectedByLandlord": 0,
    "rented": 0,
    "cancelled": 0,
    "copyright": "Copyright Bostadsregistret AB",
    "timeWhenLandlordMaySeeApplicants": 1622498400
  },
  {
    "id": 8193,
    "storedMatchingId": 0,
    "searchingFor": 0,
    "suburbId": 3,
    "suburbName": "Huskvarna",
    "cityId": 9,
    "cityName": "Jönköping",
    "address": "Hakarpsvägen 50",
    "addressCity": "Huskvarna ",
    "contractType": 0,
    "contractLength": 3,
    "otherLength": "0",
    "area": 28,
    "rooms": 1,
    "rent": 3780,
    "warm": 2,
    "elevator": false,
    "balcony": false,
    "floor1Sub": false,
    "floor1Ground": false,
    "floor1Stairs": true,
    "attic": false,
    "duplex": false,
    "furnished": false,
    "entryDate": "2021-09-01",
    "floor": 1,
    "reference": "",
    "postalCode": "56138",
    "otherInfo": "Ommålad. Parkering. Nykaklat badrum. ",
    "adText": "Lägenhet om 1rok i Huskvarna, Jönköping. \tOmmålad. Parkering. Nykaklat badrum. @bostadsregistret #bostadsregistret ",
    "statusText": "Published",
    "statusCode": 1,
    "hidden": false,
    "comments": "",
    "mayManageApplicants": true,
    "registerIdSelectedByLandlord": 0,
    "rented": 0,
    "cancelled": 0,
    "copyright": "Copyright Bostadsregistret AB",
    "timeWhenLandlordMaySeeApplicants": 1622412000
  },
  {
    "id": 8192,
    "storedMatchingId": 0,
    "searchingFor": 0,
    "suburbId": 3,
    "suburbName": "Huskvarna",
    "cityId": 9,
    "cityName": "Jönköping",
    "address": "Storgatan 6",
    "addressCity": "Huskvarna ",
    "contractType": 0,
    "contractLength": 3,
    "otherLength": "0",
    "area": 45,
    "rooms": 1,
    "rent": 4332,
    "warm": 2,
    "elevator": false,
    "balcony": false,
    "floor1Sub": false,
    "floor1Ground": false,
    "floor1Stairs": true,
    "attic": false,
    "duplex": false,
    "furnished": false,
    "entryDate": "2021-09-01",
    "floor": 1,
    "reference": "",
    "postalCode": "56142",
    "otherInfo": "Kabel-tv. Fiber ",
    "adText": "Lägenhet om 1rok i Huskvarna, Jönköping. Fiber. Kabel-tv. @bostadsregistret #bostadsregistret ",
    "statusText": "Published",
    "statusCode": 1,
    "hidden": false,
    "comments": "",
    "mayManageApplicants": true,
    "registerIdSelectedByLandlord": 0,
    "rented": 0,
    "cancelled": 0,
    "copyright": "Copyright Bostadsregistret AB",
    "timeWhenLandlordMaySeeApplicants": 1622412000
  },
  {
    "id": 8190,
    "storedMatchingId": 0,
    "searchingFor": 0,
    "suburbId": 1681,
    "suburbName": "Centralt",
    "cityId": 184,
    "cityName": "Nässjö",
    "address": "Sörängsvägen 16",
    "addressCity": "Nässjö",
    "contractType": 0,
    "contractLength": 3,
    "otherLength": "0",
    "area": 180,
    "rooms": 7,
    "rent": 11714,
    "warm": 2,
    "elevator": false,
    "balcony": true,
    "floor1Sub": false,
    "floor1Ground": false,
    "floor1Stairs": true,
    "attic": false,
    "duplex": false,
    "furnished": false,
    "entryDate": "2021-09-01",
    "floor": 1,
    "reference": "",
    "postalCode": "57138",
    "otherInfo": "Unik lägenhet centralt i charmigt sekelskifteshus med tillhörande trädgård. Parkettgolv, golvvärme, braskamin och öppen spis är exempel på vad som finns i lägenheten. Fiber samt TV med alla film/sportkanaler etc tillkommer med 400:-/mån. Hushållsel tillkommer utöver ovan.",
    "adText": "Lägenhet om 7rok i Centrala Nässjö. Unik lägenhet centralt i charmigt sekelskifteshus med tillhörande trädgård. Parkettgolv, golvvärme, braskamin och öppen spis är exempel på vad som finns i lägenheten. Fiber samt TV med alla film/sportkanaler etc tillkommer med 400:-/mån. Hushållsel tillkommer utöver ovan. För 3D-planritning och interiörbilder tryck på fler bilder. @bostadsregistret #bostadsregistret ",
    "statusText": "Published",
    "statusCode": 1,
    "hidden": false,
    "comments": "",
    "mayManageApplicants": true,
    "registerIdSelectedByLandlord": 0,
    "rented": 0,
    "cancelled": 0,
    "copyright": "Copyright Bostadsregistret AB",
    "timeWhenLandlordMaySeeApplicants": 1622412000
  },
  {
    "id": 8189,
    "storedMatchingId": 0,
    "searchingFor": 0,
    "suburbId": 1681,
    "suburbName": "Centralt",
    "cityId": 184,
    "cityName": "Nässjö",
    "address": "Prästgatan 12",
    "addressCity": "NÄSSJÖ",
    "contractType": 0,
    "contractLength": 3,
    "otherLength": "0",
    "area": 55,
    "rooms": 2,
    "rent": 6710,
    "warm": 2,
    "elevator": false,
    "balcony": false,
    "floor1Sub": false,
    "floor1Ground": false,
    "floor1Stairs": true,
    "attic": false,
    "duplex": false,
    "furnished": false,
    "entryDate": "2021-06-01",
    "floor": 1,
    "reference": "",
    "postalCode": "57131",
    "otherInfo": "Våra lägenheter ligger i centrala Nässjö bara några kvarter från stationen, stadshuset, biblioteket och den vackra Stadsparken och Ingsbergssjön\n",
    "adText": "Lägenhet om 2rok i Centrala Nässjö. I centrala Nässjö bara några kvarter från stationen, stadshuset, biblioteket och den vackra Stadsparken och Ingsbergssjön. @bostadsregistret #bostadsregistret ",
    "statusText": "Published",
    "statusCode": 1,
    "hidden": false,
    "comments": "",
    "mayManageApplicants": true,
    "registerIdSelectedByLandlord": 0,
    "rented": 0,
    "cancelled": 0,
    "copyright": "Copyright Bostadsregistret AB",
    "timeWhenLandlordMaySeeApplicants": 1622325600
  },
  {
    "id": 8183,
    "storedMatchingId": 0,
    "searchingFor": 0,
    "suburbId": 2052,
    "suburbName": "Forserum",
    "cityId": 184,
    "cityName": "Nässjö",
    "address": "Jönköpingsvägen 1C",
    "addressCity": "Forserum",
    "contractType": 0,
    "contractLength": 3,
    "otherLength": "0",
    "area": 39,
    "rooms": 1,
    "rent": 3568,
    "warm": 2,
    "elevator": false,
    "balcony": false,
    "floor1Sub": false,
    "floor1Ground": false,
    "floor1Stairs": false,
    "attic": false,
    "duplex": false,
    "furnished": false,
    "entryDate": "2021-08-01",
    "floor": 2,
    "reference": "",
    "postalCode": "57178",
    "otherInfo": "",
    "adText": "Lägenhet om 1rok i Forserum, mellan Jönköping och Nässjö. Endast 2 mil till Jönköping och med bra förbindelser. @bostadsregistret #bostadsregistret ",
    "statusText": "Published",
    "statusCode": 1,
    "hidden": false,
    "comments": "",
    "mayManageApplicants": true,
    "registerIdSelectedByLandlord": 0,
    "rented": 0,
    "cancelled": 0,
    "copyright": "Copyright Bostadsregistret AB",
    "timeWhenLandlordMaySeeApplicants": 1622239200
  },
  {
    "id": 8181,
    "storedMatchingId": 0,
    "searchingFor": 0,
    "suburbId": 1681,
    "suburbName": "Centralt",
    "cityId": 184,
    "cityName": "Nässjö",
    "address": "Skogsvägen 5",
    "addressCity": "Nässjö",
    "contractType": 0,
    "contractLength": 3,
    "otherLength": "0",
    "area": 63,
    "rooms": 2,
    "rent": 5055,
    "warm": 2,
    "elevator": false,
    "balcony": true,
    "floor1Sub": false,
    "floor1Ground": false,
    "floor1Stairs": false,
    "attic": false,
    "duplex": false,
    "furnished": false,
    "entryDate": "2021-09-01",
    "floor": 2,
    "reference": "",
    "postalCode": "57140",
    "otherInfo": "",
    "adText": "Lägenhet om 2rok i Centrala Nässjö. Balkong. @bostadsregistret #bostadsregistret ",
    "statusText": "Published",
    "statusCode": 1,
    "hidden": false,
    "comments": "",
    "mayManageApplicants": true,
    "registerIdSelectedByLandlord": 0,
    "rented": 0,
    "cancelled": 0,
    "copyright": "Copyright Bostadsregistret AB",
    "timeWhenLandlordMaySeeApplicants": 1622239200
  },
  {
    "id": 8103,
    "storedMatchingId": 0,
    "searchingFor": 0,
    "suburbId": 1925,
    "suburbName": "Runneryd",
    "cityId": 184,
    "cityName": "Nässjö",
    "address": "Långgatan 28",
    "addressCity": "Nässjö",
    "contractType": 0,
    "contractLength": 3,
    "otherLength": "0",
    "area": 30,
    "rooms": 1,
    "rent": 3400,
    "warm": 2,
    "elevator": false,
    "balcony": false,
    "floor1Sub": false,
    "floor1Ground": false,
    "floor1Stairs": false,
    "attic": false,
    "duplex": false,
    "furnished": false,
    "entryDate": "2021-07-01",
    "floor": 3,
    "reference": "",
    "postalCode": "57136",
    "otherInfo": "nyrenoverade och fin lägenheter. Passar ensamboende eller student, referens från förra hyresvärden krävs, hyresgäst med jobb och inga betalnings anmärkningar önskas",
    "adText": "Lägenhet om 1rok i Nässjö, Runneryd. Nyrenoverad och fin lägenhet. Passar ensamboende eller student eller kanske övernattningslägenhet. Nära till busshållplats. Referens från tidigare  hyresvärden krävs. Fast inkomst alternativt studiemedel krävs. Ej betalningsanmärkningar. @bostadsregistret #bostadsregistret ",
    "statusText": "Published",
    "statusCode": 1,
    "hidden": false,
    "comments": "",
    "mayManageApplicants": true,
    "registerIdSelectedByLandlord": 0,
    "rented": 0,
    "cancelled": 0,
    "copyright": "Copyright Bostadsregistret AB",
    "timeWhenLandlordMaySeeApplicants": 1620424800
  },
  {
    "id": 8175,
    "storedMatchingId": 0,
    "searchingFor": 0,
    "suburbId": 1929,
    "suburbName": "Handskeryd",
    "cityId": 184,
    "cityName": "Nässjö",
    "address": "Queckfeldtsgatan 57",
    "addressCity": "Nässjö",
    "contractType": 0,
    "contractLength": 3,
    "otherLength": "0",
    "area": 60,
    "rooms": 2,
    "rent": 5171,
    "warm": 2,
    "elevator": false,
    "balcony": true,
    "floor1Sub": false,
    "floor1Ground": false,
    "floor1Stairs": false,
    "attic": false,
    "duplex": false,
    "furnished": false,
    "entryDate": "2021-07-02",
    "floor": 1,
    "reference": "",
    "postalCode": "57140",
    "otherInfo": "",
    "adText": "Lägenhet om 2rok i Nässjö, Handskeryd. Balkong. @bostadsregistret #bostadsregistret ",
    "statusText": "Published",
    "statusCode": 1,
    "hidden": false,
    "comments": "",
    "mayManageApplicants": true,
    "registerIdSelectedByLandlord": 0,
    "rented": 0,
    "cancelled": 0,
    "copyright": "Copyright Bostadsregistret AB",
    "timeWhenLandlordMaySeeApplicants": 1621893600
  },
  {
    "id": 8170,
    "storedMatchingId": 0,
    "searchingFor": 0,
    "suburbId": 2052,
    "suburbName": "Forserum",
    "cityId": 184,
    "cityName": "Nässjö",
    "address": "Storgatan 5",
    "addressCity": "Forserum",
    "contractType": 0,
    "contractLength": 3,
    "otherLength": "0",
    "area": 64,
    "rooms": 2,
    "rent": 6248,
    "warm": 2,
    "elevator": false,
    "balcony": true,
    "floor1Sub": false,
    "floor1Ground": false,
    "floor1Stairs": false,
    "attic": false,
    "duplex": false,
    "furnished": false,
    "entryDate": "2021-08-01",
    "floor": 2,
    "reference": "",
    "postalCode": "57177",
    "otherInfo": "2ROK med totalrenoverat kök och badrum. ",
    "adText": "Lägenhet om 2rok i Forserum, mellan Jönköping och Nässjö. 2ROK med totalrenoverat kök och badrum. Endast 2 mil till Jönköping och bra förbindelser. @bostadsregistret #bostadsregistret ",
    "statusText": "Published",
    "statusCode": 1,
    "hidden": false,
    "comments": "",
    "mayManageApplicants": true,
    "registerIdSelectedByLandlord": 0,
    "rented": 0,
    "cancelled": 0,
    "copyright": "Copyright Bostadsregistret AB",
    "timeWhenLandlordMaySeeApplicants": 1621807200
  },
  {
    "id": 8168,
    "storedMatchingId": 0,
    "searchingFor": 0,
    "suburbId": 2052,
    "suburbName": "Forserum",
    "cityId": 184,
    "cityName": "Nässjö",
    "address": "Storgatan 3B",
    "addressCity": "Forserum",
    "contractType": 0,
    "contractLength": 3,
    "otherLength": "0",
    "area": 86,
    "rooms": 4,
    "rent": 8120,
    "warm": 2,
    "elevator": false,
    "balcony": true,
    "floor1Sub": false,
    "floor1Ground": false,
    "floor1Stairs": false,
    "attic": false,
    "duplex": false,
    "furnished": false,
    "entryDate": "2021-08-01",
    "floor": 3,
    "reference": "",
    "postalCode": "57177",
    "otherInfo": "Nymålad lägenhet med totalrenoverat kök och badrum med tvättmaskin och torktumlare.",
    "adText": "Lägenhet om 4rok i Forserum, mellan Jönköping och Nässjö. Nymålad lägenhet med totalrenoverat kök och badrum med tvättmaskin och torktumlare. Endast 2 mil till Jönköping och med bra förbindelser. @bostadsregistret #bostadsregistret ",
    "statusText": "Published",
    "statusCode": 1,
    "hidden": false,
    "comments": "",
    "mayManageApplicants": true,
    "registerIdSelectedByLandlord": 0,
    "rented": 0,
    "cancelled": 0,
    "copyright": "Copyright Bostadsregistret AB",
    "timeWhenLandlordMaySeeApplicants": 1621807200
  },
  {
    "id": 8169,
    "storedMatchingId": 0,
    "searchingFor": 0,
    "suburbId": 2052,
    "suburbName": "Forserum",
    "cityId": 184,
    "cityName": "Nässjö",
    "address": "Storgatan 12B",
    "addressCity": "Forserum",
    "contractType": 0,
    "contractLength": 3,
    "otherLength": "0",
    "area": 74,
    "rooms": 2,
    "rent": 7185,
    "warm": 2,
    "elevator": false,
    "balcony": false,
    "floor1Sub": false,
    "floor1Ground": false,
    "floor1Stairs": false,
    "attic": false,
    "duplex": false,
    "furnished": false,
    "entryDate": "2021-07-19",
    "floor": 2,
    "reference": "",
    "postalCode": "57177",
    "otherInfo": "2,5 rums lägenhet med modernt kök och badrum med tvättmaskin.",
    "adText": "Lägenhet om 2,5rok i Forserum, mellan Jönköping och Nässjö. 2,5 rums lägenhet med modernt kök och badrum med tvättmaskin. Endast 2 mil till Jönköping och med bra förbindelser. @bostadsregistret #bostadsregistret ",
    "statusText": "Published",
    "statusCode": 1,
    "hidden": false,
    "comments": "",
    "mayManageApplicants": true,
    "registerIdSelectedByLandlord": 0,
    "rented": 0,
    "cancelled": 0,
    "copyright": "Copyright Bostadsregistret AB",
    "timeWhenLandlordMaySeeApplicants": 1621807200
  },
  {
    "id": 8143,
    "storedMatchingId": 0,
    "searchingFor": 0,
    "suburbId": 1924,
    "suburbName": "Centrum",
    "cityId": 184,
    "cityName": "Nässjö",
    "address": "Bangårdsgatan 24A",
    "addressCity": "Nässjö",
    "contractType": 0,
    "contractLength": 3,
    "otherLength": "0",
    "area": 90,
    "rooms": 3,
    "rent": 8000,
    "warm": 2,
    "elevator": false,
    "balcony": true,
    "floor1Sub": false,
    "floor1Ground": false,
    "floor1Stairs": false,
    "attic": false,
    "duplex": false,
    "furnished": false,
    "entryDate": "2021-08-01",
    "floor": 2,
    "reference": "",
    "postalCode": "57132",
    "otherInfo": "Fin, ljus lägenhet med hög standard och högt i tak. Nytt kök, kaklat badrum med golvvärme, parkettgolv. Tvättstuga i källaren. Tillgång till gemensam balkong samt gemensam trädgård m uteplats.",
    "adText": "Lägenhet om 3rok i Nässjö Centrum.  Fin, ljus lägenhet med hög standard och högt i tak. Nytt kök, kaklat badrum med golvvärme, parkettgolv. Tvättstuga i källaren. Tillgång till gemensam balkong samt gemensam trädgård m uteplats. @bostadsregistret #bostadsregistret ",
    "statusText": "Published",
    "statusCode": 1,
    "hidden": false,
    "comments": "",
    "mayManageApplicants": true,
    "registerIdSelectedByLandlord": 0,
    "rented": 0,
    "cancelled": 0,
    "copyright": "Copyright Bostadsregistret AB",
    "timeWhenLandlordMaySeeApplicants": 1621116000
  },
  {
    "id": 8146,
    "storedMatchingId": 0,
    "searchingFor": 0,
    "suburbId": 3790,
    "suburbName": "Ingsberg",
    "cityId": 184,
    "cityName": "Nässjö",
    "address": "Espingsgatan 10 ",
    "addressCity": "Nässjö",
    "contractType": 0,
    "contractLength": 3,
    "otherLength": "0",
    "area": 37,
    "rooms": 1,
    "rent": 3417,
    "warm": 2,
    "elevator": false,
    "balcony": false,
    "floor1Sub": false,
    "floor1Ground": false,
    "floor1Stairs": false,
    "attic": false,
    "duplex": false,
    "furnished": false,
    "entryDate": "2021-08-01",
    "floor": 2,
    "reference": "ES101102",
    "postalCode": "57136",
    "otherInfo": "",
    "adText": "Lägenhet om 1rok i Nässjö, Ingsberg. ",
    "statusText": "Published",
    "statusCode": 1,
    "hidden": false,
    "comments": "",
    "mayManageApplicants": true,
    "registerIdSelectedByLandlord": 0,
    "rented": 0,
    "cancelled": 0,
    "copyright": "Copyright Bostadsregistret AB",
    "timeWhenLandlordMaySeeApplicants": 1621116000
  },
  {
    "id": 8141,
    "storedMatchingId": 0,
    "searchingFor": 0,
    "suburbId": 1681,
    "suburbName": "Centralt",
    "cityId": 184,
    "cityName": "Nässjö",
    "address": "Änggatan 9 ",
    "addressCity": "Nässjö",
    "contractType": 0,
    "contractLength": 3,
    "otherLength": "0",
    "area": 84,
    "rooms": 3,
    "rent": 6587,
    "warm": 2,
    "elevator": false,
    "balcony": false,
    "floor1Sub": false,
    "floor1Ground": false,
    "floor1Stairs": true,
    "attic": false,
    "duplex": false,
    "furnished": false,
    "entryDate": "2021-08-01",
    "floor": 1,
    "reference": "ÄN91006",
    "postalCode": "57142",
    "otherInfo": "",
    "adText": "Lägenhet om 3rok i Centrala Nässjö. ",
    "statusText": "Published",
    "statusCode": 1,
    "hidden": false,
    "comments": "",
    "mayManageApplicants": true,
    "registerIdSelectedByLandlord": 0,
    "rented": 0,
    "cancelled": 0,
    "copyright": "Copyright Bostadsregistret AB",
    "timeWhenLandlordMaySeeApplicants": 1621029600
  },
  {
    "id": 8138,
    "storedMatchingId": 0,
    "searchingFor": 0,
    "suburbId": 1939,
    "suburbName": "Malmbäck",
    "cityId": 184,
    "cityName": "Nässjö",
    "address": "Klockargårdsgatan 4",
    "addressCity": "Malmbäck",
    "contractType": 0,
    "contractLength": 3,
    "otherLength": "0",
    "area": 42,
    "rooms": 1,
    "rent": 3587,
    "warm": 2,
    "elevator": false,
    "balcony": false,
    "floor1Sub": false,
    "floor1Ground": false,
    "floor1Stairs": true,
    "attic": false,
    "duplex": false,
    "furnished": false,
    "entryDate": "2021-09-01",
    "floor": 1,
    "reference": "",
    "postalCode": "57168",
    "otherInfo": "1rok 42m2 uthyres i Malmbäck. Gemensam tvättstuga I källaren. Värme och vatten ingår. Fiber är installerat.",
    "adText": "Lägenhet om 1rok i Malmbäck, Nässjö kommun. 1rok 42m2 uthyres i Malmbäck. Gemensam tvättstuga I källaren. Värme och vatten ingår. Fiber är installerat. @bostadsregistret #bostadsregistret ",
    "statusText": "Published",
    "statusCode": 1,
    "hidden": false,
    "comments": "",
    "mayManageApplicants": true,
    "registerIdSelectedByLandlord": 0,
    "rented": 0,
    "cancelled": 0,
    "copyright": "Copyright Bostadsregistret AB",
    "timeWhenLandlordMaySeeApplicants": 1621029600
  },
  {
    "id": 8135,
    "storedMatchingId": 0,
    "searchingFor": 0,
    "suburbId": 2532,
    "suburbName": "Torpa",
    "cityId": 9,
    "cityName": "Jönköping",
    "address": "Brahegatan 48",
    "addressCity": "Jönköping",
    "contractType": 0,
    "contractLength": 3,
    "otherLength": "0",
    "area": 64,
    "rooms": 2,
    "rent": 8931,
    "warm": 2,
    "elevator": true,
    "balcony": true,
    "floor1Sub": false,
    "floor1Ground": true,
    "floor1Stairs": false,
    "attic": false,
    "duplex": false,
    "furnished": false,
    "entryDate": "2021-09-01",
    "floor": 1,
    "reference": "1005",
    "postalCode": "55334",
    "otherInfo": "Nyligen renoverad.\n",
    "adText": "Lägenhet om 2rok i Jönköping, Torpa. Balkong. Hiss. Nydligen renoverad. @bostadsregistret #bostadsregistret ",
    "statusText": "Published",
    "statusCode": 1,
    "hidden": false,
    "comments": "",
    "mayManageApplicants": true,
    "registerIdSelectedByLandlord": 0,
    "rented": 0,
    "cancelled": 0,
    "copyright": "Copyright Bostadsregistret AB",
    "timeWhenLandlordMaySeeApplicants": 1620770400
  },
  {
    "id": 8131,
    "storedMatchingId": 0,
    "searchingFor": 0,
    "suburbId": 1927,
    "suburbName": "Åker",
    "cityId": 184,
    "cityName": "Nässjö",
    "address": "Stolmakaregatan 17",
    "addressCity": "Nässjö",
    "contractType": 0,
    "contractLength": 3,
    "otherLength": "0",
    "area": 63,
    "rooms": 2,
    "rent": 5790,
    "warm": 2,
    "elevator": false,
    "balcony": true,
    "floor1Sub": false,
    "floor1Ground": false,
    "floor1Stairs": true,
    "attic": false,
    "duplex": false,
    "furnished": false,
    "entryDate": "2021-07-01",
    "floor": 1,
    "reference": "tg",
    "postalCode": "57137",
    "otherInfo": "Gavellägenhet på 1 vån med trevlig planlösning..",
    "adText": "Lägenhet om 2rok i Nässjö, Åker. Gavellägenhet på 1 vån med trevlig planlösning. @bostadsregistret #bostadsregistret ",
    "statusText": "Published",
    "statusCode": 1,
    "hidden": false,
    "comments": "",
    "mayManageApplicants": true,
    "registerIdSelectedByLandlord": 0,
    "rented": 0,
    "cancelled": 0,
    "copyright": "Copyright Bostadsregistret AB",
    "timeWhenLandlordMaySeeApplicants": 1620684000
  },
  {
    "id": 8130,
    "storedMatchingId": 0,
    "searchingFor": 0,
    "suburbId": 1927,
    "suburbName": "Åker",
    "cityId": 184,
    "cityName": "Nässjö",
    "address": "Stolmakaregatan 9 A",
    "addressCity": "Nässjö",
    "contractType": 0,
    "contractLength": 3,
    "otherLength": "0",
    "area": 69,
    "rooms": 3,
    "rent": 6482,
    "warm": 2,
    "elevator": false,
    "balcony": true,
    "floor1Sub": false,
    "floor1Ground": false,
    "floor1Stairs": false,
    "attic": false,
    "duplex": false,
    "furnished": false,
    "entryDate": "2021-08-01",
    "floor": 2,
    "reference": "gavellägenhet",
    "postalCode": "57137",
    "otherInfo": "Charmig gavellägenheten med bra planlösning. Nära till skola, dagis och köpstaden..",
    "adText": "Lägenhet om 3rok i Nässjö, Åker. Balkong. Charmig gavellägenheten med bra planlösning. Nära till skola, dagis och köpstaden. @bostadsregistret #bostadsregistret ",
    "statusText": "Published",
    "statusCode": 1,
    "hidden": false,
    "comments": "",
    "mayManageApplicants": true,
    "registerIdSelectedByLandlord": 0,
    "rented": 0,
    "cancelled": 0,
    "copyright": "Copyright Bostadsregistret AB",
    "timeWhenLandlordMaySeeApplicants": 1620684000
  },
  {
    "id": 8129,
    "storedMatchingId": 0,
    "searchingFor": 0,
    "suburbId": 2210,
    "suburbName": "Centrum",
    "cityId": 9,
    "cityName": "Jönköping",
    "address": "Östra Storgatan 14",
    "addressCity": "Jönköping",
    "contractType": 0,
    "contractLength": 3,
    "otherLength": "0",
    "area": 54,
    "rooms": 2,
    "rent": 8120,
    "warm": 2,
    "elevator": false,
    "balcony": true,
    "floor1Sub": false,
    "floor1Ground": false,
    "floor1Stairs": false,
    "attic": false,
    "duplex": false,
    "furnished": false,
    "entryDate": "2021-06-01",
    "floor": 3,
    "reference": "",
    "postalCode": "55321",
    "otherInfo": "Mycket fräsch lägenhet, totalrenoverad 2018. Egen tvm och tt.",
    "adText": "Lägenhet om 2rok i Jönköping Centrum. Balkong. Mycket fräsch lägenhet, totalrenoverad 2018. Egen tvättmaskin och torktumlare. @bostadsregistret #bostadsregistret ",
    "statusText": "Published",
    "statusCode": 1,
    "hidden": false,
    "comments": "",
    "mayManageApplicants": true,
    "registerIdSelectedByLandlord": 0,
    "rented": 0,
    "cancelled": 0,
    "copyright": "Copyright Bostadsregistret AB",
    "timeWhenLandlordMaySeeApplicants": 1620684000
  },
  {
    "id": 8128,
    "storedMatchingId": 0,
    "searchingFor": 0,
    "suburbId": 1681,
    "suburbName": "Centralt",
    "cityId": 184,
    "cityName": "Nässjö",
    "address": "Lövåsgatan 29",
    "addressCity": "Nässjö",
    "contractType": 0,
    "contractLength": 3,
    "otherLength": "0",
    "area": 52,
    "rooms": 2,
    "rent": 4855,
    "warm": 2,
    "elevator": false,
    "balcony": false,
    "floor1Sub": false,
    "floor1Ground": false,
    "floor1Stairs": false,
    "attic": false,
    "duplex": false,
    "furnished": false,
    "entryDate": "2021-07-01",
    "floor": 2,
    "reference": "",
    "postalCode": "57140",
    "otherInfo": "",
    "adText": "Lägenhet om 2rok i Centrala Nässjö. @bostadsregistret #bostadsregistret ",
    "statusText": "Published",
    "statusCode": 1,
    "hidden": false,
    "comments": "",
    "mayManageApplicants": true,
    "registerIdSelectedByLandlord": 0,
    "rented": 0,
    "cancelled": 0,
    "copyright": "Copyright Bostadsregistret AB",
    "timeWhenLandlordMaySeeApplicants": 1620684000
  },
  {
    "id": 8118,
    "storedMatchingId": 0,
    "searchingFor": 0,
    "suburbId": 3,
    "suburbName": "Huskvarna",
    "cityId": 9,
    "cityName": "Jönköping",
    "address": "Järnvägsgatan 5",
    "addressCity": "Huskvarna",
    "contractType": 0,
    "contractLength": 2,
    "otherLength": "0",
    "area": 80,
    "rooms": 3,
    "rent": 7890,
    "warm": 2,
    "elevator": false,
    "balcony": false,
    "floor1Sub": false,
    "floor1Ground": false,
    "floor1Stairs": false,
    "attic": false,
    "duplex": false,
    "furnished": false,
    "entryDate": "2021-07-01",
    "floor": 3,
    "reference": "",
    "postalCode": "56130",
    "otherInfo": "",
    "adText": "Lägenhet om 3rok i Huskvarna, Jönköping. @bostadsregistret #bostadsregistret ",
    "statusText": "Published",
    "statusCode": 1,
    "hidden": false,
    "comments": "",
    "mayManageApplicants": true,
    "registerIdSelectedByLandlord": 0,
    "rented": 0,
    "cancelled": 0,
    "copyright": "Copyright Bostadsregistret AB",
    "timeWhenLandlordMaySeeApplicants": 1620597600
  },
  {
    "id": 8117,
    "storedMatchingId": 0,
    "searchingFor": 0,
    "suburbId": 2240,
    "suburbName": "Skillingaryd",
    "cityId": 253,
    "cityName": "Vaggeryd",
    "address": "Läkaregatan 3",
    "addressCity": "Skillingaryd",
    "contractType": 0,
    "contractLength": 3,
    "otherLength": "0",
    "area": 69,
    "rooms": 3,
    "rent": 8783,
    "warm": 1,
    "elevator": false,
    "balcony": true,
    "floor1Sub": false,
    "floor1Ground": true,
    "floor1Stairs": false,
    "attic": false,
    "duplex": false,
    "furnished": false,
    "entryDate": "2021-06-30",
    "floor": 1,
    "reference": "C-1001",
    "postalCode": "56831",
    "otherInfo": "",
    "adText": "Lägenhet om 3rok i Skillingaryd, Vaggeryds kommun. Pendlingsavstånd till Jönköping, Värnamo, Vaggeryd och Sävsjö. @bostadsregistret #bostadsregistret ",
    "statusText": "Published",
    "statusCode": 1,
    "hidden": false,
    "comments": "",
    "mayManageApplicants": true,
    "registerIdSelectedByLandlord": 0,
    "rented": 0,
    "cancelled": 0,
    "copyright": "Copyright Bostadsregistret AB",
    "timeWhenLandlordMaySeeApplicants": 1620597600
  },
  {
    "id": 8112,
    "storedMatchingId": 0,
    "searchingFor": 0,
    "suburbId": 1924,
    "suburbName": "Centrum",
    "cityId": 184,
    "cityName": "Nässjö",
    "address": "Rådhusgatan 21 B",
    "addressCity": "Nässjö",
    "contractType": 0,
    "contractLength": 3,
    "otherLength": "0",
    "area": 100,
    "rooms": 4,
    "rent": 9450,
    "warm": 2,
    "elevator": false,
    "balcony": false,
    "floor1Sub": false,
    "floor1Ground": false,
    "floor1Stairs": false,
    "attic": false,
    "duplex": false,
    "furnished": false,
    "entryDate": "2021-06-01",
    "floor": 2,
    "reference": "21 B,  TG",
    "postalCode": "57131",
    "otherInfo": "Charmig lägenhet i en charmig fastighet. Bra planlösning och högt mysigt i tak. Tvättmaskin ingår..",
    "adText": "Lägenhet om 4rok i Nässjö Centrum. Charmig lägenhet i en charmig fastighet. Bra planlösning och högt mysigt i tak. Tvättmaskin ingår. Mitt i centrum vid tåget. @bostadsregistret #bostadsregistret ",
    "statusText": "Published",
    "statusCode": 1,
    "hidden": false,
    "comments": "",
    "mayManageApplicants": true,
    "registerIdSelectedByLandlord": 0,
    "rented": 0,
    "cancelled": 0,
    "copyright": "Copyright Bostadsregistret AB",
    "timeWhenLandlordMaySeeApplicants": 1620597600
  },
  {
    "id": 8115,
    "storedMatchingId": 0,
    "searchingFor": 0,
    "suburbId": 1681,
    "suburbName": "Centralt",
    "cityId": 184,
    "cityName": "Nässjö",
    "address": "Rådhusgatan 37 B",
    "addressCity": "Nässjö",
    "contractType": 0,
    "contractLength": 3,
    "otherLength": "0",
    "area": 38,
    "rooms": 1,
    "rent": 3626,
    "warm": 2,
    "elevator": false,
    "balcony": false,
    "floor1Sub": false,
    "floor1Ground": false,
    "floor1Stairs": false,
    "attic": false,
    "duplex": false,
    "furnished": false,
    "entryDate": "2021-08-01",
    "floor": 3,
    "reference": "E1021",
    "postalCode": "57132",
    "otherInfo": "En ljus och trevlig 1 ROK i centrala Nässjö är ledig från 15/6 eller enligt överenskommelse, senast 1/8. \nBra planlösning med sovalkov och ett rymligt möblerbart kök. TV-kanaler via Com Hem ingår. Möjlighet till garageplats i källaren.\nNärhet till allt, bara någon minuts promenad till centrum och stationen.",
    "adText": "Lägenhet om 1rok i Centrala Nässjö. En ljus och trevlig 1 ROK i centrala Nässjö är ledig 15/6 senast 1/8.Bra planlösning med sovalkov och ett rymligt möblerbart kök. TV-kanaler via Com Hem ingår. Möjlighet till garageplats i källaren. Närhet till allt, bara någon minuts promenad till centrum och stationen. @bostadsregistret #bostadsregistret ",
    "statusText": "Published",
    "statusCode": 1,
    "hidden": false,
    "comments": "",
    "mayManageApplicants": true,
    "registerIdSelectedByLandlord": 0,
    "rented": 0,
    "cancelled": 0,
    "copyright": "Copyright Bostadsregistret AB",
    "timeWhenLandlordMaySeeApplicants": 1620597600
  },
  {
    "id": 8111,
    "storedMatchingId": 0,
    "searchingFor": 0,
    "suburbId": 1924,
    "suburbName": "Centrum",
    "cityId": 184,
    "cityName": "Nässjö",
    "address": "Postgatan 1 A",
    "addressCity": "Nässjö",
    "contractType": 0,
    "contractLength": 3,
    "otherLength": "0",
    "area": 108,
    "rooms": 4,
    "rent": 12878,
    "warm": 2,
    "elevator": true,
    "balcony": true,
    "floor1Sub": false,
    "floor1Ground": false,
    "floor1Stairs": false,
    "attic": false,
    "duplex": false,
    "furnished": false,
    "entryDate": "2021-07-01",
    "floor": 1,
    "reference": "1104",
    "postalCode": "57132",
    "otherInfo": "1104",
    "adText": "Lägenhet om 4rok i Nässjö Centrum. Balkong. Hiss. Mitt i Centrum. Bra läge vid tåg/buss. @bostadsregistret #bostadsregistret ",
    "statusText": "Published",
    "statusCode": 1,
    "hidden": false,
    "comments": "",
    "mayManageApplicants": true,
    "registerIdSelectedByLandlord": 0,
    "rented": 0,
    "cancelled": 0,
    "copyright": "Copyright Bostadsregistret AB",
    "timeWhenLandlordMaySeeApplicants": 1620597600
  },
  {
    "id": 8098,
    "storedMatchingId": 0,
    "searchingFor": 0,
    "suburbId": 1929,
    "suburbName": "Handskeryd",
    "cityId": 184,
    "cityName": "Nässjö",
    "address": "Queckfeldtsgatan 47",
    "addressCity": "Nässjö",
    "contractType": 0,
    "contractLength": 3,
    "otherLength": "0",
    "area": 73,
    "rooms": 2,
    "rent": 6996,
    "warm": 2,
    "elevator": false,
    "balcony": true,
    "floor1Sub": false,
    "floor1Ground": false,
    "floor1Stairs": false,
    "attic": false,
    "duplex": false,
    "furnished": false,
    "entryDate": "2021-07-01",
    "floor": 2,
    "reference": "",
    "postalCode": "57140",
    "otherInfo": "Mycket fin lägenhet i lugnt hus. Kaklat badrum.",
    "adText": "Lägenhet om 2rok i Nässjö, Handskeryd. Balkong. Mycket fin lägenhet i lugnt hus. Kaklat badrum. @bostadsregistret #bostadsregistret ",
    "statusText": "Published",
    "statusCode": 1,
    "hidden": false,
    "comments": "",
    "mayManageApplicants": true,
    "registerIdSelectedByLandlord": 0,
    "rented": 0,
    "cancelled": 0,
    "copyright": "Copyright Bostadsregistret AB",
    "timeWhenLandlordMaySeeApplicants": 1620165600
  },
  {
    "id": 8079,
    "storedMatchingId": 0,
    "searchingFor": 0,
    "suburbId": 2240,
    "suburbName": "Skillingaryd",
    "cityId": 253,
    "cityName": "Vaggeryd",
    "address": "Läkaregatan 3",
    "addressCity": "Skillingaryd",
    "contractType": 0,
    "contractLength": 3,
    "otherLength": "0",
    "area": 35,
    "rooms": 1,
    "rent": 5115,
    "warm": 1,
    "elevator": false,
    "balcony": false,
    "floor1Sub": false,
    "floor1Ground": true,
    "floor1Stairs": false,
    "attic": false,
    "duplex": false,
    "furnished": false,
    "entryDate": "2021-08-01",
    "floor": 1,
    "reference": "C-1004",
    "postalCode": "56831",
    "otherInfo": "",
    "adText": "Lägenhet om 1rok i Skillingaryd, Vaggeryds kommun. Pendlingsavstånd till Värnamo och Jönköping. @bostadsregistret #bostadsregistret ",
    "statusText": "Published",
    "statusCode": 1,
    "hidden": false,
    "comments": "",
    "mayManageApplicants": true,
    "registerIdSelectedByLandlord": 0,
    "rented": 0,
    "cancelled": 0,
    "copyright": "Copyright Bostadsregistret AB",
    "timeWhenLandlordMaySeeApplicants": 1619906400
  },
  {
    "id": 8065,
    "storedMatchingId": 0,
    "searchingFor": 0,
    "suburbId": 1681,
    "suburbName": "Centralt",
    "cityId": 184,
    "cityName": "Nässjö",
    "address": "Rådhusgatan 42",
    "addressCity": "Nässjö",
    "contractType": 0,
    "contractLength": 3,
    "otherLength": "0",
    "area": 42,
    "rooms": 1,
    "rent": 3689,
    "warm": 2,
    "elevator": true,
    "balcony": true,
    "floor1Sub": false,
    "floor1Ground": false,
    "floor1Stairs": false,
    "attic": false,
    "duplex": false,
    "furnished": false,
    "entryDate": "2021-07-01",
    "floor": 2,
    "reference": "B1004",
    "postalCode": "57132",
    "otherInfo": "En ljus och trevlig 1ROK i centrala Nässjö blir ledig 1/7.\nHär har du ett bekvämt boende med närhet till allt med både hiss och balkong. Bra förvaringsmöjligheter inne i lägenheten och även förråd i källaren. De 12 första TV-kanaler igår i hyran, via Com Hem.\nMöjlighet till parkeringsplats finns.",
    "adText": "Lägenhet om 1rok i Centrala Nässjö. En ljus och trevlig 1ROK i centrala Nässjö blir ledig 1/7. Här har du ett bekvämt boende med närhet till allt med både hiss och balkong. Bra förvaringsmöjligheter inne i lägenheten och även förråd i källaren. De 12 första TV-kanaler igår i hyran, via Com Hem. Möjlighet till parkeringsplats finns. @bostadsregistret #bostadsregistret ",
    "statusText": "Published",
    "statusCode": 1,
    "hidden": false,
    "comments": "",
    "mayManageApplicants": true,
    "registerIdSelectedByLandlord": 0,
    "rented": 0,
    "cancelled": 0,
    "copyright": "Copyright Bostadsregistret AB",
    "timeWhenLandlordMaySeeApplicants": 1619474400
  },
  {
    "id": 8053,
    "storedMatchingId": 0,
    "searchingFor": 0,
    "suburbId": 17,
    "suburbName": "Norrahammar",
    "cityId": 9,
    "cityName": "Jönköping",
    "address": "Spånbergsvägen 1",
    "addressCity": "Norrahammar",
    "contractType": 0,
    "contractLength": 3,
    "otherLength": "0",
    "area": 110,
    "rooms": 4,
    "rent": 9010,
    "warm": 2,
    "elevator": false,
    "balcony": false,
    "floor1Sub": false,
    "floor1Ground": false,
    "floor1Stairs": true,
    "attic": false,
    "duplex": false,
    "furnished": false,
    "entryDate": "2021-08-01",
    "floor": 1,
    "reference": "",
    "postalCode": "56232",
    "otherInfo": "",
    "adText": "Lägenhet om 4rok i Jönköping, Norrahammar. @bostadsregistret #bostadsregistret ",
    "statusText": "Published",
    "statusCode": 1,
    "hidden": false,
    "comments": "",
    "mayManageApplicants": true,
    "registerIdSelectedByLandlord": 0,
    "rented": 0,
    "cancelled": 0,
    "copyright": "Copyright Bostadsregistret AB",
    "timeWhenLandlordMaySeeApplicants": 1619215200
  },
  {
    "id": 8051,
    "storedMatchingId": 0,
    "searchingFor": 0,
    "suburbId": 1681,
    "suburbName": "Centralt",
    "cityId": 184,
    "cityName": "Nässjö",
    "address": "Parkgatan 10 B",
    "addressCity": "Nässjö",
    "contractType": 0,
    "contractLength": 3,
    "otherLength": "0",
    "area": 50,
    "rooms": 2,
    "rent": 5000,
    "warm": 2,
    "elevator": false,
    "balcony": true,
    "floor1Sub": false,
    "floor1Ground": true,
    "floor1Stairs": false,
    "attic": false,
    "duplex": false,
    "furnished": false,
    "entryDate": "2021-05-01",
    "floor": 1,
    "reference": "1006",
    "postalCode": "57138",
    "otherInfo": "Gårdshus",
    "adText": "Lägenhet om 2rok i Centrala Nässjö. Gårdshus. Passar för en person. @bostadsregistret #bostadsregistret ",
    "statusText": "Published",
    "statusCode": 1,
    "hidden": false,
    "comments": "",
    "mayManageApplicants": true,
    "registerIdSelectedByLandlord": 0,
    "rented": 0,
    "cancelled": 0,
    "copyright": "Copyright Bostadsregistret AB",
    "timeWhenLandlordMaySeeApplicants": 1619128800
  },
  {
    "id": 8036,
    "storedMatchingId": 0,
    "searchingFor": 0,
    "suburbId": 2840,
    "suburbName": "Hembygdsparken",
    "cityId": 184,
    "cityName": "Nässjö",
    "address": "Hembygdsgatan 6 ",
    "addressCity": "Nässjö",
    "contractType": 0,
    "contractLength": 3,
    "otherLength": "0",
    "area": 70,
    "rooms": 3,
    "rent": 5991,
    "warm": 2,
    "elevator": false,
    "balcony": true,
    "floor1Sub": false,
    "floor1Ground": false,
    "floor1Stairs": false,
    "attic": false,
    "duplex": false,
    "furnished": false,
    "entryDate": "2021-08-01",
    "floor": 1,
    "reference": "Lgh 1101",
    "postalCode": "57135",
    "otherInfo": "Lägenhet om 3 rok i trevligt område nära centrum, simhall, gym mm. Uteplats. Fräsch gemensam tvättstuga i källare. Möjlighet att hyra garage finns. ",
    "adText": "Lägenhet om 3rok i Nässjö, Hembygdsparken. Lägenhet om 3 rok i trevligt område nära centrum, simhall, gym mm. Uteplats. Fräsch gemensam tvättstuga i källare. Möjlighet att hyra garage finns. @bostadsregistret #bostadsregistret ",
    "statusText": "Published",
    "statusCode": 1,
    "hidden": false,
    "comments": "",
    "mayManageApplicants": true,
    "registerIdSelectedByLandlord": 0,
    "rented": 0,
    "cancelled": 0,
    "copyright": "Copyright Bostadsregistret AB",
    "timeWhenLandlordMaySeeApplicants": 1618696800
  },
  {
    "id": 8030,
    "storedMatchingId": 0,
    "searchingFor": 0,
    "suburbId": 1939,
    "suburbName": "Malmbäck",
    "cityId": 184,
    "cityName": "Nässjö",
    "address": "Parkstigen 26",
    "addressCity": "Malmbäck",
    "contractType": 0,
    "contractLength": 3,
    "otherLength": "0",
    "area": 69,
    "rooms": 3,
    "rent": 5454,
    "warm": 2,
    "elevator": false,
    "balcony": true,
    "floor1Sub": false,
    "floor1Ground": false,
    "floor1Stairs": false,
    "attic": false,
    "duplex": false,
    "furnished": false,
    "entryDate": "2021-07-01",
    "floor": 2,
    "reference": "",
    "postalCode": "57168",
    "otherInfo": "Renoverad lägenhet i Malmbäck uthyres. 3rok med balkong.  Gemensam tvättstuga i källaren.  Värme och vatten igår. Fiber finns indraget. ",
    "adText": "Lägenhet om 3rok  i Malmbäck, Nässjö kommun. Renoverad lägenhet i Malmbäck uthyres. 3rok med balkong. Gemensam tvättstuga i källaren. Värme och vatten igår. Fiber finns indraget. @bostadsregistret #bostadsregistret ",
    "statusText": "Published",
    "statusCode": 1,
    "hidden": false,
    "comments": "",
    "mayManageApplicants": true,
    "registerIdSelectedByLandlord": 0,
    "rented": 0,
    "cancelled": 0,
    "copyright": "Copyright Bostadsregistret AB",
    "timeWhenLandlordMaySeeApplicants": 1618610400
  },
  {
    "id": 8007,
    "storedMatchingId": 0,
    "searchingFor": 0,
    "suburbId": 3,
    "suburbName": "Huskvarna",
    "cityId": 9,
    "cityName": "Jönköping",
    "address": "Ådalsvägen 24",
    "addressCity": "Huskvarna",
    "contractType": 0,
    "contractLength": 3,
    "otherLength": "0",
    "area": 35,
    "rooms": 1,
    "rent": 4759,
    "warm": 2,
    "elevator": false,
    "balcony": false,
    "floor1Sub": true,
    "floor1Ground": false,
    "floor1Stairs": false,
    "attic": false,
    "duplex": false,
    "furnished": false,
    "entryDate": "2021-07-01",
    "floor": 1,
    "reference": "",
    "postalCode": "56130",
    "otherInfo": "Trevlig etta med mindre köksdel.",
    "adText": "Lägenhet om 1rok i Huskvarna, Jönköping. Trevlig etta med mindre köksdel. @bostadsregistret #bostadsregistret ",
    "statusText": "Published",
    "statusCode": 1,
    "hidden": false,
    "comments": "",
    "mayManageApplicants": true,
    "registerIdSelectedByLandlord": 0,
    "rented": 0,
    "cancelled": 0,
    "copyright": "Copyright Bostadsregistret AB",
    "timeWhenLandlordMaySeeApplicants": 1618092000
  },
  {
    "id": 8010,
    "storedMatchingId": 0,
    "searchingFor": 3,
    "suburbId": 1927,
    "suburbName": "Åker",
    "cityId": 184,
    "cityName": "Nässjö",
    "address": "Fabriksgatan 6",
    "addressCity": "NÄSSJÖ",
    "contractType": 0,
    "contractLength": 3,
    "otherLength": "0",
    "area": 94,
    "rooms": 4,
    "rent": 11454,
    "warm": 1,
    "elevator": false,
    "balcony": true,
    "floor1Sub": false,
    "floor1Ground": true,
    "floor1Stairs": true,
    "attic": false,
    "duplex": false,
    "furnished": false,
    "entryDate": "2021-05-01",
    "floor": 1,
    "reference": "",
    "postalCode": "57142",
    "otherInfo": "VISNING PÅ PLATS 27 April kl. 17.00. VÄLKOMNA!\n\n\nSISTA HÖRNRADHUSET!\nNybyggt radhus på SNICKAREN på 94 m2 4 ROK med 7 m2 inglasat uterum samt liten täppa utanför.",
    "adText": "Lägenhet/Radhus om 4rok i Nässjö, Åker. SISTA HÖRNRADHUSET! Nybyggt radhus på SNICKAREN på 94 m2 4 ROK med 7 m2 inglasat uterum samt liten täppa utanför. @bostadsregistret #bostadsregistret ",
    "statusText": "Published",
    "statusCode": 1,
    "hidden": false,
    "comments": "",
    "mayManageApplicants": true,
    "registerIdSelectedByLandlord": 0,
    "rented": 0,
    "cancelled": 0,
    "copyright": "Copyright Bostadsregistret AB",
    "timeWhenLandlordMaySeeApplicants": 1618092000
  },
  {
    "id": 8009,
    "storedMatchingId": 0,
    "searchingFor": 3,
    "suburbId": 1927,
    "suburbName": "Åker",
    "cityId": 184,
    "cityName": "Nässjö",
    "address": "Fabriksgatan 6",
    "addressCity": "NÄSSJÖ",
    "contractType": 0,
    "contractLength": 3,
    "otherLength": "0",
    "area": 94,
    "rooms": 4,
    "rent": 10993,
    "warm": 1,
    "elevator": false,
    "balcony": true,
    "floor1Sub": false,
    "floor1Ground": true,
    "floor1Stairs": true,
    "attic": false,
    "duplex": false,
    "furnished": false,
    "entryDate": "2021-05-01",
    "floor": 1,
    "reference": "",
    "postalCode": "57142",
    "otherInfo": "VISNING PÅ PLATS 27 April kl. 17.00. VÄLKOMNA!\n\nNybyggt radhus på SNICKAREN på 94 m2 4 ROK med 7 m2 inglasat uterum samt liten täppa utanför. Detta är ett mellan radhus.\n",
    "adText": "Lägenhet/Radhus om 4rok i Nässjö, Åker. Nybyggt radhus på SNICKAREN på 94 m2 4 ROK med 7 m2 inglasat uterum samt liten täppa utanför. Detta är ett mellanradhus. @bostadsregistret #bostadsregistret ",
    "statusText": "Published",
    "statusCode": 1,
    "hidden": false,
    "comments": "",
    "mayManageApplicants": true,
    "registerIdSelectedByLandlord": 0,
    "rented": 0,
    "cancelled": 0,
    "copyright": "Copyright Bostadsregistret AB",
    "timeWhenLandlordMaySeeApplicants": 1618092000
  },
  {
    "id": 7992,
    "storedMatchingId": 0,
    "searchingFor": 0,
    "suburbId": 1929,
    "suburbName": "Handskeryd",
    "cityId": 184,
    "cityName": "Nässjö",
    "address": "Sörängsvägen 13",
    "addressCity": "Nässjö",
    "contractType": 0,
    "contractLength": 3,
    "otherLength": "0",
    "area": 90,
    "rooms": 3,
    "rent": 8500,
    "warm": 2,
    "elevator": false,
    "balcony": true,
    "floor1Sub": false,
    "floor1Ground": false,
    "floor1Stairs": true,
    "attic": false,
    "duplex": false,
    "furnished": false,
    "entryDate": "2021-07-01",
    "floor": 1,
    "reference": "",
    "postalCode": "57138",
    "otherInfo": "Rök &amp;amp;amp;amp; djurfritt, eget garage, egen ingång, egen tvättmaskin/torktumlare, egen diskmaskin. Ni når mig på mobilnummer 070-5493975",
    "adText": "Stor Lägenhet om 3rok i Nässjö, Handskeryd. Balkong. Eget garage. egen ingång, egen tvättmaskin/torktumlare, egen diskmaskin. @bostadsregistret #bostadsregistret ",
    "statusText": "Published",
    "statusCode": 1,
    "hidden": false,
    "comments": "",
    "mayManageApplicants": true,
    "registerIdSelectedByLandlord": 0,
    "rented": 0,
    "cancelled": 0,
    "copyright": "Copyright Bostadsregistret AB",
    "timeWhenLandlordMaySeeApplicants": 1617573600
  },
  {
    "id": 7982,
    "storedMatchingId": 0,
    "searchingFor": 0,
    "suburbId": 1929,
    "suburbName": "Handskeryd",
    "cityId": 184,
    "cityName": "Nässjö",
    "address": "Arne Fagers Gata 6A",
    "addressCity": "NÄSSJÖ",
    "contractType": 0,
    "contractLength": 3,
    "otherLength": "0",
    "area": 79,
    "rooms": 4,
    "rent": 10304,
    "warm": 1,
    "elevator": true,
    "balcony": true,
    "floor1Sub": false,
    "floor1Ground": true,
    "floor1Stairs": true,
    "attic": false,
    "duplex": false,
    "furnished": false,
    "entryDate": "2021-10-01",
    "floor": 1,
    "reference": "",
    "postalCode": "57140",
    "otherInfo": "Boka din lägenhet nu på nyproducerade Chokladhjulet 2. Ange lägenhetsnummer du önskar. mer info på www.f4h.se eller maila på info@f4h.se",
    "adText": "Lägenhet om 4rok i Nässjö, Handskeryd. Balkong. Hiss. Bilderna är exempelbilder. @bostadsregistret #bostadsregistret ",
    "statusText": "Published",
    "statusCode": 1,
    "hidden": false,
    "comments": "",
    "mayManageApplicants": true,
    "registerIdSelectedByLandlord": 0,
    "rented": 0,
    "cancelled": 0,
    "copyright": "Copyright Bostadsregistret AB",
    "timeWhenLandlordMaySeeApplicants": 1617487200
  },
  {
    "id": 7981,
    "storedMatchingId": 0,
    "searchingFor": 0,
    "suburbId": 1929,
    "suburbName": "Handskeryd",
    "cityId": 184,
    "cityName": "Nässjö",
    "address": "Arne Fagers Gata 6A",
    "addressCity": "NÄSSJÖ",
    "contractType": 0,
    "contractLength": 3,
    "otherLength": "0",
    "area": 52,
    "rooms": 2,
    "rent": 7074,
    "warm": 1,
    "elevator": true,
    "balcony": true,
    "floor1Sub": false,
    "floor1Ground": true,
    "floor1Stairs": true,
    "attic": false,
    "duplex": false,
    "furnished": false,
    "entryDate": "2021-10-01",
    "floor": 1,
    "reference": "",
    "postalCode": "57140",
    "otherInfo": "Boka din lägenhet nu på nyproducerade Chokladhjulet 2. Ange lägenhetsnummer du önskar. mer info på www.f4h.se eller maila på info@f4h.se",
    "adText": "Lägenhet om 2rok  i Nässjö, Handskeryd. Balkong. Hiss. Bilderna är exempelbilder. @bostadsregistret #bostadsregistret ",
    "statusText": "Published",
    "statusCode": 1,
    "hidden": false,
    "comments": "",
    "mayManageApplicants": true,
    "registerIdSelectedByLandlord": 0,
    "rented": 0,
    "cancelled": 0,
    "copyright": "Copyright Bostadsregistret AB",
    "timeWhenLandlordMaySeeApplicants": 1617487200
  },
  {
    "id": 7980,
    "storedMatchingId": 0,
    "searchingFor": 0,
    "suburbId": 1929,
    "suburbName": "Handskeryd",
    "cityId": 184,
    "cityName": "Nässjö",
    "address": "Arne Fagers Gata 6",
    "addressCity": "NÄSSJÖ",
    "contractType": 0,
    "contractLength": 3,
    "otherLength": "0",
    "area": 64,
    "rooms": 3,
    "rent": 8843,
    "warm": 1,
    "elevator": true,
    "balcony": true,
    "floor1Sub": false,
    "floor1Ground": true,
    "floor1Stairs": true,
    "attic": false,
    "duplex": false,
    "furnished": false,
    "entryDate": "2021-10-01",
    "floor": 1,
    "reference": "",
    "postalCode": "57140",
    "otherInfo": "Boka din lägenhet nu på nyproducerade Chokladhjulet 2. Ange lägenhetsnummer du önskar. mer info på www.f4h.se eller maila på info@f4h.se",
    "adText": "Lägenhet om 3rok i Nässjö, Handskeryd. Balkong. Hiss. Bilderna är exempelbilder. @bostadsregistret #bostadsregistret ",
    "statusText": "Published",
    "statusCode": 1,
    "hidden": false,
    "comments": "",
    "mayManageApplicants": true,
    "registerIdSelectedByLandlord": 0,
    "rented": 0,
    "cancelled": 0,
    "copyright": "Copyright Bostadsregistret AB",
    "timeWhenLandlordMaySeeApplicants": 1617487200
  },
  {
    "id": 7946,
    "storedMatchingId": 0,
    "searchingFor": 1,
    "suburbId": 2210,
    "suburbName": "Centrum",
    "cityId": 9,
    "cityName": "Jönköping",
    "address": "Östra Storgatan 39",
    "addressCity": "Jönköping",
    "contractType": 0,
    "contractLength": 3,
    "otherLength": "0",
    "area": 14,
    "rooms": 1,
    "rent": 2981,
    "warm": 2,
    "elevator": false,
    "balcony": false,
    "floor1Sub": false,
    "floor1Ground": false,
    "floor1Stairs": false,
    "attic": false,
    "duplex": false,
    "furnished": true,
    "entryDate": "2021-06-01",
    "floor": 2,
    "reference": "R10-119",
    "postalCode": "55321",
    "otherInfo": "Hyresgästen delar kök, wc och duschar med övriga 9 studenter/hyresgäster.\nInternet via Junet ingår samt kabel-tv via ComHem.",
    "adText": "Hyresrätt/Studentrum i Centrala Jönköping. Hyresgästen delar kök, wc och duschar med övriga 9 studenter/hyresgäster. Internet via Junet ingår samt kabel-tv via ComHem. @bostadsregistret #bostadsregistret ",
    "statusText": "Published",
    "statusCode": 1,
    "hidden": false,
    "comments": "",
    "mayManageApplicants": true,
    "registerIdSelectedByLandlord": 0,
    "rented": 0,
    "cancelled": 0,
    "copyright": "Copyright Bostadsregistret AB",
    "timeWhenLandlordMaySeeApplicants": 1616281200
  },
  {
    "id": 7940,
    "storedMatchingId": 0,
    "searchingFor": 0,
    "suburbId": 1927,
    "suburbName": "Åker",
    "cityId": 184,
    "cityName": "Nässjö",
    "address": "Änggatan 9 ",
    "addressCity": "Nässjö ",
    "contractType": 0,
    "contractLength": 3,
    "otherLength": "0",
    "area": 33,
    "rooms": 1,
    "rent": 3635,
    "warm": 2,
    "elevator": false,
    "balcony": false,
    "floor1Sub": false,
    "floor1Ground": false,
    "floor1Stairs": true,
    "attic": false,
    "duplex": false,
    "furnished": false,
    "entryDate": "2021-07-01",
    "floor": 1,
    "reference": "ÄN91002",
    "postalCode": "57142",
    "otherInfo": "",
    "adText": "Lägenhet om 1rok i Nässjö, Åker. ",
    "statusText": "Published",
    "statusCode": 1,
    "hidden": false,
    "comments": "",
    "mayManageApplicants": true,
    "registerIdSelectedByLandlord": 0,
    "rented": 0,
    "cancelled": 0,
    "copyright": "Copyright Bostadsregistret AB",
    "timeWhenLandlordMaySeeApplicants": 1616281200
  },
  {
    "id": 7937,
    "storedMatchingId": 0,
    "searchingFor": 1,
    "suburbId": 3524,
    "suburbName": "Bäckalyckan",
    "cityId": 9,
    "cityName": "Jönköping",
    "address": "Lyckhemsgatan 15",
    "addressCity": "Jönköping",
    "contractType": 0,
    "contractLength": 3,
    "otherLength": "0",
    "area": 20,
    "rooms": 1,
    "rent": 4000,
    "warm": 2,
    "elevator": false,
    "balcony": false,
    "floor1Sub": false,
    "floor1Ground": true,
    "floor1Stairs": false,
    "attic": false,
    "duplex": false,
    "furnished": true,
    "entryDate": "2021-04-01",
    "floor": 1,
    "reference": "",
    "postalCode": "55313",
    "otherInfo": "Gemensamt kök, gemensam WC/dusch, gemensam tvättstuga. \n\nLägenheten delas med två andra hyresgäster.",
    "adText": "Lägenhet/Studentrum i Jönköping, Bäckalyckan. Gemensamt kök, gemensam WC/dusch, gemensam tvättstuga. Lägenheten delas med två andra hyresgäster. @bostadsregistret #bostadsregistret ",
    "statusText": "Published",
    "statusCode": 1,
    "hidden": false,
    "comments": "",
    "mayManageApplicants": true,
    "registerIdSelectedByLandlord": 0,
    "rented": 0,
    "cancelled": 0,
    "copyright": "Copyright Bostadsregistret AB",
    "timeWhenLandlordMaySeeApplicants": 1616194800
  },
  {
    "id": 7918,
    "storedMatchingId": 0,
    "searchingFor": 0,
    "suburbId": 1681,
    "suburbName": "Centralt",
    "cityId": 184,
    "cityName": "Nässjö",
    "address": "Bangårdsgatan 24 B",
    "addressCity": "Nässjö ",
    "contractType": 0,
    "contractLength": 3,
    "otherLength": "0",
    "area": 40,
    "rooms": 1,
    "rent": 4500,
    "warm": 2,
    "elevator": false,
    "balcony": false,
    "floor1Sub": false,
    "floor1Ground": false,
    "floor1Stairs": false,
    "attic": true,
    "duplex": false,
    "furnished": false,
    "entryDate": "2021-07-01",
    "floor": 3,
    "reference": "",
    "postalCode": "57132",
    "otherInfo": "Fin 1,5 m kokvrå. Helkaklat badrum m golvvärme. Tillgång till gemensam trädgård, tvättstuga i källaren. Helkaklat badrum m golvvärme. Ev möjlighet till tidigare tillträde.",
    "adText": "Lägenhet om 1,5rokv i Centrala Nässjö. Fin 1,5 m kokvrå. Helkaklat badrum m golvvärme. Tillgång till gemensam trädgård, tvättstuga i källaren. Helkaklat badrum m golvvärme. Ev möjlighet till tidigare tillträde. @bostadsregistret #bostadsregistret ",
    "statusText": "Published",
    "statusCode": 1,
    "hidden": false,
    "comments": "",
    "mayManageApplicants": true,
    "registerIdSelectedByLandlord": 0,
    "rented": 0,
    "cancelled": 0,
    "copyright": "Copyright Bostadsregistret AB",
    "timeWhenLandlordMaySeeApplicants": 1615935600
  },
  {
    "id": 7909,
    "storedMatchingId": 0,
    "searchingFor": 0,
    "suburbId": 2240,
    "suburbName": "Skillingaryd",
    "cityId": 253,
    "cityName": "Vaggeryd",
    "address": "Läkaregatan 3",
    "addressCity": "Skillingaryd",
    "contractType": 0,
    "contractLength": 3,
    "otherLength": "0",
    "area": 52,
    "rooms": 2,
    "rent": 6716,
    "warm": 1,
    "elevator": false,
    "balcony": false,
    "floor1Sub": false,
    "floor1Ground": true,
    "floor1Stairs": false,
    "attic": false,
    "duplex": false,
    "furnished": false,
    "entryDate": "2021-06-01",
    "floor": 1,
    "reference": "A-1002",
    "postalCode": "56831",
    "otherInfo": "",
    "adText": "Lägenhet om 2rok i Skillingaryd, Vaggeryds kommun.  Pendlingsavstånd till Jönköping, Värnamo, Vaggeryd och Sävsjö. @bostadsregistret #bostadsregistret ",
    "statusText": "Published",
    "statusCode": 1,
    "hidden": false,
    "comments": "",
    "mayManageApplicants": true,
    "registerIdSelectedByLandlord": 0,
    "rented": 0,
    "cancelled": 0,
    "copyright": "Copyright Bostadsregistret AB",
    "timeWhenLandlordMaySeeApplicants": 1615676400
  },
  {
    "id": 7906,
    "storedMatchingId": 0,
    "searchingFor": 0,
    "suburbId": 1939,
    "suburbName": "Malmbäck",
    "cityId": 184,
    "cityName": "Nässjö",
    "address": "Torget 4",
    "addressCity": "Malmbäck",
    "contractType": 0,
    "contractLength": 3,
    "otherLength": "0",
    "area": 65,
    "rooms": 2,
    "rent": 4836,
    "warm": 1,
    "elevator": false,
    "balcony": true,
    "floor1Sub": false,
    "floor1Ground": false,
    "floor1Stairs": false,
    "attic": false,
    "duplex": false,
    "furnished": false,
    "entryDate": "2021-06-01",
    "floor": 2,
    "reference": "",
    "postalCode": "57168",
    "otherInfo": "2rok uthyres i Centrala Malmbäck. Balkong ut mot torget ca 50m till affär, 50m till busshållplats, ca 50m till tågstation. Gemensam tvättstuga. Egen elpanna i varje lägenhet. ",
    "adText": "Lägenhet om 2rok i Malmbäck, Nässjö kommun. 2rok uthyres i Centrala Malmbäck. Balkong ut mot torget ca 50m till affär, 50m till busshållplats, ca 50m till tågstation. Gemensam tvättstuga. Egen elpanna i varje lägenhet. @bostadsregistret #bostadsregistret ",
    "statusText": "Published",
    "statusCode": 1,
    "hidden": false,
    "comments": "",
    "mayManageApplicants": true,
    "registerIdSelectedByLandlord": 0,
    "rented": 0,
    "cancelled": 0,
    "copyright": "Copyright Bostadsregistret AB",
    "timeWhenLandlordMaySeeApplicants": 1615676400
  },
  {
    "id": 7831,
    "storedMatchingId": 0,
    "searchingFor": 0,
    "suburbId": 2240,
    "suburbName": "Skillingaryd",
    "cityId": 253,
    "cityName": "Vaggeryd",
    "address": "Läkaregatan 3",
    "addressCity": "Skillingaryd",
    "contractType": 0,
    "contractLength": 3,
    "otherLength": "0",
    "area": 52,
    "rooms": 2,
    "rent": 7130,
    "warm": 1,
    "elevator": false,
    "balcony": true,
    "floor1Sub": false,
    "floor1Ground": true,
    "floor1Stairs": false,
    "attic": false,
    "duplex": false,
    "furnished": false,
    "entryDate": "2021-03-01",
    "floor": 1,
    "reference": "A-1001",
    "postalCode": "56831",
    "otherInfo": "",
    "adText": "Lägenhet om 2rok i Skillingaryd, Vaggeryds kommun. Balkong. Pendlingsavstånd till Vaggeryd, Jönköping och Värnamo. @bostadsregistret #bostadsregistret ",
    "statusText": "Published",
    "statusCode": 1,
    "hidden": false,
    "comments": "",
    "mayManageApplicants": true,
    "registerIdSelectedByLandlord": 0,
    "rented": 0,
    "cancelled": 0,
    "copyright": "Copyright Bostadsregistret AB",
    "timeWhenLandlordMaySeeApplicants": 1613170800
  },
  {
    "id": 7791,
    "storedMatchingId": 0,
    "searchingFor": 0,
    "suburbId": 17,
    "suburbName": "Norrahammar",
    "cityId": 9,
    "cityName": "Jönköping",
    "address": "Sjögatan  9E",
    "addressCity": "NORRAHAMMAR",
    "contractType": 0,
    "contractLength": 3,
    "otherLength": "0",
    "area": 58,
    "rooms": 2,
    "rent": 8200,
    "warm": 2,
    "elevator": false,
    "balcony": true,
    "floor1Sub": false,
    "floor1Ground": false,
    "floor1Stairs": false,
    "attic": false,
    "duplex": false,
    "furnished": false,
    "entryDate": "2021-09-01",
    "floor": 2,
    "reference": "",
    "postalCode": "56232",
    "otherInfo": "Nyproducerad lägenhet  våning  2\nnära skog o vandringsleder. nära Åsasjön, Busshållplats vid tomtgränsen. \nNära till  Norrahammars centrum , ca 1mil  till centrala Jönköping",
    "adText": "Lägenhet om 2rok i Jönköping, Norrahammar. Nyproducerad lgh, våning 2 nära skog och vandringsleder. Nära Åsasjön, Busshållsplats vid tomtgräns, Nära till Norrahammar Centrum, ca 1 mil till Centrala Jönköping. @bostadsregistret #bostadsregistret ",
    "statusText": "Published",
    "statusCode": 1,
    "hidden": false,
    "comments": "",
    "mayManageApplicants": true,
    "registerIdSelectedByLandlord": 0,
    "rented": 0,
    "cancelled": 0,
    "copyright": "Copyright Bostadsregistret AB",
    "timeWhenLandlordMaySeeApplicants": 1612566000
  },
  {
    "id": 7701,
    "storedMatchingId": 0,
    "searchingFor": 0,
    "suburbId": 1927,
    "suburbName": "Åker",
    "cityId": 184,
    "cityName": "Nässjö",
    "address": "Mellangatan 25",
    "addressCity": "Nässjö",
    "contractType": 0,
    "contractLength": 3,
    "otherLength": "0",
    "area": 55,
    "rooms": 2,
    "rent": 5840,
    "warm": 2,
    "elevator": false,
    "balcony": true,
    "floor1Sub": false,
    "floor1Ground": false,
    "floor1Stairs": true,
    "attic": false,
    "duplex": false,
    "furnished": false,
    "entryDate": "2021-01-08",
    "floor": 1,
    "reference": "",
    "postalCode": "57142",
    "otherInfo": "",
    "adText": "Lägenhet om 2rok i Nässjö, Åker. Balkong. Tvättstuga i källaren. Två trappsteg upp så nästan markplan. @bostadsregistret #bostadsregistret ",
    "statusText": "Published",
    "statusCode": 1,
    "hidden": false,
    "comments": "",
    "mayManageApplicants": true,
    "registerIdSelectedByLandlord": 0,
    "rented": 0,
    "cancelled": 0,
    "copyright": "Copyright Bostadsregistret AB",
    "timeWhenLandlordMaySeeApplicants": 1610492400
  },
  {
    "id": 7699,
    "storedMatchingId": 0,
    "searchingFor": 0,
    "suburbId": 1927,
    "suburbName": "Åker",
    "cityId": 184,
    "cityName": "Nässjö",
    "address": "Mellangatan 23",
    "addressCity": "Nässjö",
    "contractType": 0,
    "contractLength": 3,
    "otherLength": "0",
    "area": 51,
    "rooms": 1,
    "rent": 4200,
    "warm": 2,
    "elevator": false,
    "balcony": false,
    "floor1Sub": false,
    "floor1Ground": false,
    "floor1Stairs": false,
    "attic": false,
    "duplex": false,
    "furnished": false,
    "entryDate": "2021-03-01",
    "floor": 2,
    "reference": "",
    "postalCode": "57142",
    "otherInfo": "",
    "adText": "Lägenhet om 1rok i Nässjö, Åker. Tvättstuga i källaren. @bostadsregistret #bostadsregistret ",
    "statusText": "Published",
    "statusCode": 1,
    "hidden": false,
    "comments": "",
    "mayManageApplicants": true,
    "registerIdSelectedByLandlord": 0,
    "rented": 0,
    "cancelled": 0,
    "copyright": "Copyright Bostadsregistret AB",
    "timeWhenLandlordMaySeeApplicants": 1610492400
  },
  {
    "id": 7563,
    "storedMatchingId": 0,
    "searchingFor": 0,
    "suburbId": 1930,
    "suburbName": "Nyhem",
    "cityId": 184,
    "cityName": "Nässjö",
    "address": "Skogsvägen 25",
    "addressCity": "Nässjö",
    "contractType": 0,
    "contractLength": 3,
    "otherLength": "0",
    "area": 69,
    "rooms": 2,
    "rent": 6806,
    "warm": 2,
    "elevator": false,
    "balcony": false,
    "floor1Sub": false,
    "floor1Ground": false,
    "floor1Stairs": false,
    "attic": false,
    "duplex": false,
    "furnished": false,
    "entryDate": "2020-12-01",
    "floor": 2,
    "reference": "",
    "postalCode": "57138",
    "otherInfo": "Trevlig lägenhet på 2:a våningen. Hushållsel tillkommer.",
    "adText": "Lägenhet om 2rok i Nässjö, Nyhem. Trevlig lägenhet på 2:a våningen. Hushållsel tillkommer. @bostadsregistret #bostadsregistret ",
    "statusText": "Published",
    "statusCode": 1,
    "hidden": false,
    "comments": "",
    "mayManageApplicants": true,
    "registerIdSelectedByLandlord": 0,
    "rented": 0,
    "cancelled": 0,
    "copyright": "Copyright Bostadsregistret AB",
    "timeWhenLandlordMaySeeApplicants": 1606604400
  },
  {
    "id": 7450,
    "storedMatchingId": 0,
    "searchingFor": 0,
    "suburbId": 1930,
    "suburbName": "Nyhem",
    "cityId": 184,
    "cityName": "Nässjö",
    "address": "Ingsbergsgatan 82",
    "addressCity": "Nässjö",
    "contractType": 0,
    "contractLength": 3,
    "otherLength": "0",
    "area": 55,
    "rooms": 2,
    "rent": 4521,
    "warm": 2,
    "elevator": false,
    "balcony": true,
    "floor1Sub": false,
    "floor1Ground": false,
    "floor1Stairs": false,
    "attic": false,
    "duplex": false,
    "furnished": false,
    "entryDate": "2021-02-01",
    "floor": 2,
    "reference": "",
    "postalCode": "57138",
    "otherInfo": "",
    "adText": "Lägenhet om 2rok i Nässjö, Nyhem. @bostadsregistret #bostadsregistret ",
    "statusText": "Published",
    "statusCode": 1,
    "hidden": false,
    "comments": "",
    "mayManageApplicants": true,
    "registerIdSelectedByLandlord": 0,
    "rented": 0,
    "cancelled": 0,
    "copyright": "Copyright Bostadsregistret AB",
    "timeWhenLandlordMaySeeApplicants": 1604185200
  },
  {
    "id": 7446,
    "storedMatchingId": 0,
    "searchingFor": 0,
    "suburbId": 1927,
    "suburbName": "Åker",
    "cityId": 184,
    "cityName": "Nässjö",
    "address": "Bryggaregatan 5",
    "addressCity": "Nässjö",
    "contractType": 0,
    "contractLength": 3,
    "otherLength": "0",
    "area": 49,
    "rooms": 1,
    "rent": 3643,
    "warm": 2,
    "elevator": false,
    "balcony": false,
    "floor1Sub": false,
    "floor1Ground": false,
    "floor1Stairs": false,
    "attic": true,
    "duplex": false,
    "furnished": false,
    "entryDate": "2021-02-01",
    "floor": 3,
    "reference": "",
    "postalCode": "57141",
    "otherInfo": "",
    "adText": "Lägenhet om 1rok i Nässjö, Åker. @bostadsregistret #bostadsregistret ",
    "statusText": "Published",
    "statusCode": 1,
    "hidden": false,
    "comments": "",
    "mayManageApplicants": true,
    "registerIdSelectedByLandlord": 0,
    "rented": 0,
    "cancelled": 0,
    "copyright": "Copyright Bostadsregistret AB",
    "timeWhenLandlordMaySeeApplicants": 1604185200
  },
  {
    "id": 7048,
    "storedMatchingId": 0,
    "searchingFor": 0,
    "suburbId": 1924,
    "suburbName": "Centrum",
    "cityId": 184,
    "cityName": "Nässjö",
    "address": "Postgatan 1 A",
    "addressCity": "Nässjö",
    "contractType": 0,
    "contractLength": 3,
    "otherLength": "0",
    "area": 69,
    "rooms": 2,
    "rent": 8490,
    "warm": 2,
    "elevator": true,
    "balcony": false,
    "floor1Sub": false,
    "floor1Ground": false,
    "floor1Stairs": false,
    "attic": false,
    "duplex": false,
    "furnished": false,
    "entryDate": "2021-05-01",
    "floor": 2,
    "reference": "1108",
    "postalCode": "57131",
    "otherInfo": "Bo Tryggt &amp;amp;amp;amp;amp;amp; Bekvämt mitt i stan. Hög standard med tvättmaskin/torktumlare, diskmaskin och fiber.. Tillgång till samlingslokal, bastu och övernattningslägenhet. Nära till allt även tåg och buss.",
    "adText": "Lägenhet om 2rok i Nässjö Centrum. Bo Tryggt och Bekvämt mitt i stan. Hög standard med tvättmaskin/torktumlare, diskmaskin och fiber.. Tillgång till samlingslokal, bastu och övernattningslägenhet. Nära till allt även tåg och buss. @bostadsregistret #bostadsregistret ",
    "statusText": "Published",
    "statusCode": 1,
    "hidden": false,
    "comments": "",
    "mayManageApplicants": true,
    "registerIdSelectedByLandlord": 0,
    "rented": 0,
    "cancelled": 0,
    "copyright": "Copyright Bostadsregistret AB",
    "timeWhenLandlordMaySeeApplicants": 1596578400
  },
  {
    "id": 6798,
    "storedMatchingId": 0,
    "searchingFor": 0,
    "suburbId": 15,
    "suburbName": "Gränna",
    "cityId": 9,
    "cityName": "Jönköping",
    "address": "Sjögatan 75a",
    "addressCity": "Gränna",
    "contractType": 0,
    "contractLength": 3,
    "otherLength": "0",
    "area": 100,
    "rooms": 3,
    "rent": 9500,
    "warm": 2,
    "elevator": false,
    "balcony": true,
    "floor1Sub": false,
    "floor1Ground": false,
    "floor1Stairs": false,
    "attic": false,
    "duplex": false,
    "furnished": false,
    "entryDate": "2020-07-01",
    "floor": 1,
    "reference": "",
    "postalCode": "56331",
    "otherInfo": "",
    "adText": "Lägenhet om 3rok i Gränna, Jönköpings kommun. @bostadsregistret #bostadsregistret ",
    "statusText": "Published",
    "statusCode": 1,
    "hidden": false,
    "comments": "",
    "mayManageApplicants": true,
    "registerIdSelectedByLandlord": 0,
    "rented": 0,
    "cancelled": 0,
    "copyright": "Copyright Bostadsregistret AB",
    "timeWhenLandlordMaySeeApplicants": 1590616800
  },
  {
    "id": 6537,
    "storedMatchingId": 0,
    "searchingFor": 0,
    "suburbId": 3,
    "suburbName": "Huskvarna",
    "cityId": 9,
    "cityName": "Jönköping",
    "address": "Stationsgatan 5A",
    "addressCity": "Huskvarna",
    "contractType": 0,
    "contractLength": 3,
    "otherLength": "0",
    "area": 60,
    "rooms": 2,
    "rent": 7200,
    "warm": 2,
    "elevator": false,
    "balcony": false,
    "floor1Sub": false,
    "floor1Ground": false,
    "floor1Stairs": false,
    "attic": false,
    "duplex": false,
    "furnished": false,
    "entryDate": "2020-04-01",
    "floor": 1,
    "reference": "",
    "postalCode": "56133",
    "otherInfo": "",
    "adText": "Lägenhet om 2rok i Huskvarna, Jönköping. Vätterutsikt. @bostadsregistret #bostadsregistret ",
    "statusText": "Published",
    "statusCode": 1,
    "hidden": false,
    "comments": "",
    "mayManageApplicants": true,
    "registerIdSelectedByLandlord": 0,
    "rented": 0,
    "cancelled": 0,
    "copyright": "Copyright Bostadsregistret AB",
    "timeWhenLandlordMaySeeApplicants": 1584399600
  },
  {
    "id": 5391,
    "storedMatchingId": 0,
    "searchingFor": 0,
    "suburbId": 1927,
    "suburbName": "Åker",
    "cityId": 184,
    "cityName": "Nässjö",
    "address": "Brogatan 41",
    "addressCity": "Nässjö",
    "contractType": 0,
    "contractLength": 3,
    "otherLength": "0",
    "area": 90,
    "rooms": 3,
    "rent": 8600,
    "warm": 2,
    "elevator": false,
    "balcony": true,
    "floor1Sub": false,
    "floor1Ground": false,
    "floor1Stairs": false,
    "attic": false,
    "duplex": false,
    "furnished": false,
    "entryDate": "2019-05-01",
    "floor": 1,
    "reference": "",
    "postalCode": "57141",
    "otherInfo": "Lägenhet i fint skick och på bottenvåning med öppen spis i vardagsrummet i en stor villa med ca 950m2 trädgård. Stor balkong med tak. Finns diskmaskin, tvättmaskin, torktumlare. 1 parkeringsplats ingår. Ca 5 minuter ifrån centrum med bil.",
    "adText": "Lägenhet om 3rok i Nässjö, Åker. Lägenhet i fint skick och på bottenvåning med öppen spis i vardagsrummet i en stor villa med ca 950m2 trädgård. Stor balkong med tak. Diskmaskin, tvättmaskin och torktumlare. 1 parkeringsplats ingår. Ca 5 minuter ifrån centrum med bil.",
    "statusText": "Published",
    "statusCode": 1,
    "hidden": false,
    "comments": "",
    "mayManageApplicants": true,
    "registerIdSelectedByLandlord": 0,
    "rented": 0,
    "cancelled": 0,
    "copyright": "Copyright Bostadsregistret AB",
    "timeWhenLandlordMaySeeApplicants": 1555279200
  }
]
